Workbook
Name Orders: Orders!$A$1:$U$9995
Name People: People!$A$1:$B$5
Name Returns: Returns!$A$1:$A$801

Sheet Dashboard
D2: Superstore - Dashboard
D3: Total sales: | E3: 2297200.9
D4: Total profit: | E4: 286397.02
D5: Profit Ratio: | E5: =E4/E3 -> 0.12467217
D6: Profit per Order: | E6: =E4/Data[[#Totals],[Order ID]] -> 57.176487
D7: Sales per Customer: | E7: =E3/568 -> 4044.3677

Sheet Выводы
A1: Раздел | B1: Содержание
A2: Аналитическая оценка
A3: Рекомендации

Sheet Orders
A1: Row ID | B1: Order ID | C1: Order Date | D1: Ship Date | E1: Ship Mode | F1: Customer ID | G1: Customer Name | H1: Segment | I1: Country | J1: City | K1: State | L1: Postal Code | M1: Region | N1: Product ID | O1: Category | P1: Sub-Category | Q1: Product Name | R1: Sales | S1: Quantity | T1: Discount | U1: Profit | V1: Person | W1: Returned
A2: 1 | B2: CA-2018-152156 | C2: 43412 | D2: 43415 | E2: Second Class | F2: CG-12520 | G2: Claire Gute | H2: Consumer | I2: United States | J2: Henderson | K2: Kentucky | L2: 42420 | M2: South | N2: FUR-BO-10001798 | O2: Furniture | P2: Bookcases | Q2: Bush Somerset Collection Bookcase | R2: 261.96 | S2: 2 | T2: 0 | U2: 41.9136 | V2: =IF(M2=People!$B$5,People!$A$5,IF(M2=People!$B$4,People!$A$4,IF(M2=People!$B$3,People!$A$3,IF(M2=People!$B$2,People!$A$2,0)))) -> Cassandra Brandow | W2: =IFERROR(INDEX(Returns!A:A,MATCH(B2,Returns!B:B,0)),"No") -> No
A3: 2 | B3: CA-2018-152156 | C3: 43412 | D3: 43415 | E3: Second Class | F3: CG-12520 | G3: Claire Gute | H3: Consumer | I3: United States | J3: Henderson | K3: Kentucky | L3: 42420 | M3: South | N3: FUR-CH-10000454 | O3: Furniture | P3: Chairs | Q3: Hon Deluxe Fabric Upholstered Stacking Chairs, Rounded Back | R3: 731.94 | S3: 3 | T3: 0 | U3: 219.582 | V3: =IF(M3=People!$B$5,People!$A$5,IF(M3=People!$B$4,People!$A$4,IF(M3=People!$B$3,People!$A$3,IF(M3=People!$B$2,People!$A$2,0)))) -> Cassandra Brandow | W3: =IFERROR(INDEX(Returns!A:A,MATCH(B3,Returns!B:B,0)),"No") -> No
A4: 3 | B4: CA-2018-138688 | C4: 43263 | D4: 43267 | E4: Second Class | F4: DV-13045 | G4: Darrin Van Huff | H4: Corporate | I4: United States | J4: Los Angeles | K4: California | L4: 90036 | M4: West | N4: OFF-LA-10000240 | O4: Office Supplies | P4: Labels | Q4: Self-Adhesive Address Labels for Typewriters by Universal | R4: 14.62 | S4: 2 | T4: 0 | U4: 6.8714 | V4: =IF(M4=People!$B$5,People!$A$5,IF(M4=People!$B$4,People!$A$4,IF(M4=People!$B$3,People!$A$3,IF(M4=People!$B$2,People!$A$2,0)))) -> Anna Andreadi | W4: =IFERROR(INDEX(Returns!A:A,MATCH(B4,Returns!B:B,0)),"No") -> No
A5: 4 | B5: US-2017-108966 | C5: 43019 | D5: 43026 | E5: Standard Class | F5: SO-20335 | G5: Sean O'Donnell | H5: Consumer | I5: United States | J5: Fort Lauderdale | K5: Florida | L5: 33311 | M5: South | N5: FUR-TA-10000577 | O5: Furniture | P5: Tables | Q5: Bretford CR4500 Series Slim Rectangular Table | R5: 957.5775 | S5: 5 | T5: 0.45 | U5: -383.031 | V5: =IF(M5=People!$B$5,People!$A$5,IF(M5=People!$B$4,People!$A$4,IF(M5=People!$B$3,People!$A$3,IF(M5=People!$B$2,People!$A$2,0)))) -> Cassandra Brandow | W5: =IFERROR(INDEX(Returns!A:A,MATCH(B5,Returns!B:B,0)),"No") -> No
A6: 5 | B6: US-2017-108966 | C6: 43019 | D6: 43026 | E6: Standard Class | F6: SO-20335 | G6: Sean O'Donnell | H6: Consumer | I6: United States | J6: Fort Lauderdale | K6: Florida | L6: 33311 | M6: South | N6: OFF-ST-10000760 | O6: Office Supplies | P6: Storage | Q6: Eldon Fold 'N Roll Cart System | R6: 22.368 | S6: 2 | T6: 0.2 | U6: 2.5164 | V6: =IF(M6=People!$B$5,People!$A$5,IF(M6=People!$B$4,People!$A$4,IF(M6=People!$B$3,People!$A$3,IF(M6=People!$B$2,People!$A$2,0)))) -> Cassandra Brandow | W6: =IFERROR(INDEX(Returns!A:A,MATCH(B6,Returns!B:B,0)),"No") -> No
A7: 6 | B7: CA-2016-115812 | C7: 42530 | D7: 42535 | E7: Standard Class | F7: BH-11710 | G7: Brosina Hoffman | H7: Consumer | I7: United States | J7: Los Angeles | K7: California | L7: 90032 | M7: West | N7: FUR-FU-10001487 | O7: Furniture | P7: Furnishings | Q7: Eldon Expressions Wood and Plastic Desk Accessories, Cherry Wood | R7: 48.86 | S7: 7 | T7: 0 | U7: 14.1694 | V7: =IF(M7=People!$B$5,People!$A$5,IF(M7=People!$B$4,People!$A$4,IF(M7=People!$B$3,People!$A$3,IF(M7=People!$B$2,People!$A$2,0)))) -> Anna Andreadi | W7: =IFERROR(INDEX(Returns!A:A,MATCH(B7,Returns!B:B,0)),"No") -> No
A8: 7 | B8: CA-2016-115812 | C8: 42530 | D8: 42535 | E8: Standard Class | F8: BH-11710 | G8: Brosina Hoffman | H8: Consumer | I8: United States | J8: Los Angeles | K8: California | L8: 90032 | M8: West | N8: OFF-AR-10002833 | O8: Office Supplies | P8: Art | Q8: Newell 322 | R8: 7.28 | S8: 4 | T8: 0 | U8: 1.9656 | V8: =IF(M8=People!$B$5,People!$A$5,IF(M8=People!$B$4,People!$A$4,IF(M8=People!$B$3,People!$A$3,IF(M8=People!$B$2,People!$A$2,0)))) -> Anna Andreadi | W8: =IFERROR(INDEX(Returns!A:A,MATCH(B8,Returns!B:B,0)),"No") -> No
A9: 8 | B9: CA-2016-115812 | C9: 42530 | D9: 42535 | E9: Standard Class | F9: BH-11710 | G9: Brosina Hoffman | H9: Consumer | I9: United States | J9: Los Angeles | K9: California | L9: 90032 | M9: West | N9: TEC-PH-10002275 | O9: Technology | P9: Phones | Q9: Mitel 5320 IP Phone VoIP phone | R9: 907.152 | S9: 6 | T9: 0.2 | U9: 90.7152 | V9: =IF(M9=People!$B$5,People!$A$5,IF(M9=People!$B$4,People!$A$4,IF(M9=People!$B$3,People!$A$3,IF(M9=People!$B$2,People!$A$2,0)))) -> Anna Andreadi | W9: =IFERROR(INDEX(Returns!A:A,MATCH(B9,Returns!B:B,0)),"No") -> No
A10: 9 | B10: CA-2016-115812 | C10: 42530 | D10: 42535 | E10: Standard Class | F10: BH-11710 | G10: Brosina Hoffman | H10: Consumer | I10: United States | J10: Los Angeles | K10: California | L10: 90032 | M10: West | N10: OFF-BI-10003910 | O10: Office Supplies | P10: Binders | Q10: DXL Angle-View Binders with Locking Rings by Samsill | R10: 18.504 | S10: 3 | T10: 0.2 | U10: 5.7825 | V10: =IF(M10=People!$B$5,People!$A$5,IF(M10=People!$B$4,People!$A$4,IF(M10=People!$B$3,People!$A$3,IF(M10=People!$B$2,People!$A$2,0)))) -> Anna Andreadi | W10: =IFERROR(INDEX(Returns!A:A,MATCH(B10,Returns!B:B,0)),"No") -> No
A11: 10 | B11: CA-2016-115812 | C11: 42530 | D11: 42535 | E11: Standard Class | F11: BH-11710 | G11: Brosina Hoffman | H11: Consumer | I11: United States | J11: Los Angeles | K11: California | L11: 90032 | M11: West | N11: OFF-AP-10002892 | O11: Office Supplies | P11: Appliances | Q11: Belkin F5C206VTEL 6 Outlet Surge | R11: 114.9 | S11: 5 | T11: 0 | U11: 34.47 | V11: =IF(M11=People!$B$5,People!$A$5,IF(M11=People!$B$4,People!$A$4,IF(M11=People!$B$3,People!$A$3,IF(M11=People!$B$2,People!$A$2,0)))) -> Anna Andreadi | W11: =IFERROR(INDEX(Returns!A:A,MATCH(B11,Returns!B:B,0)),"No") -> No
A12: 11 | B12: CA-2016-115812 | C12: 42530 | D12: 42535 | E12: Standard Class | F12: BH-11710 | G12: Brosina Hoffman | H12: Consumer | I12: United States | J12: Los Angeles | K12: California | L12: 90032 | M12: West | N12: FUR-TA-10001539 | O12: Furniture | P12: Tables | Q12: Chromcraft Rectangular Conference Tables | R12: 1706.184 | S12: 9 | T12: 0.2 | U12: 85.3092 | V12: =IF(M12=People!$B$5,People!$A$5,IF(M12=People!$B$4,People!$A$4,IF(M12=People!$B$3,People!$A$3,IF(M12=People!$B$2,People!$A$2,0)))) -> Anna Andreadi | W12: =IFERROR(INDEX(Returns!A:A,MATCH(B12,Returns!B:B,0)),"No") -> No
A13: 12 | B13: CA-2016-115812 | C13: 42530 | D13: 42535 | E13: Standard Class | F13: BH-11710 | G13: Brosina Hoffman | H13: Consumer | I13: United States | J13: Los Angeles | K13: California | L13: 90032 | M13: West | N13: TEC-PH-10002033 | O13: Technology | P13: Phones | Q13: Konftel 250 Conference phone - Charcoal black | R13: 911.424 | S13: 4 | T13: 0.2 | U13: 68.3568 | V13: =IF(M13=People!$B$5,People!$A$5,IF(M13=People!$B$4,People!$A$4,IF(M13=People!$B$3,People!$A$3,IF(M13=People!$B$2,People!$A$2,0)))) -> Anna Andreadi | W13: =IFERROR(INDEX(Returns!A:A,MATCH(B13,Returns!B:B,0)),"No") -> No
... A2235: 2234 | B2235: CA-2017-123232 | C2235: 43083 | D2235: 43085 | E2235: Second Class | F2235: DJ-13630 | G2235: Doug Jacobs | H2235: Consumer | I2235: United States | J2235: Portland | K2235: Oregon | L2235: 97206 | M2235: West | N2235: TEC-PH-10001051 | O2235: Technology | P2235: Phones | Q2235: HTC One | R2235: 319.968 | S2235: 4 | T2235: 0.2 | U2235: 35.9964 | V2235: =IF(M2235=People!$B$5,People!$A$5,IF(M2235=People!$B$4,People!$A$4,IF(M2235=People!$B$3,People!$A$3,IF(M2235=People!$B$2,People!$A$2,0)))) -> Anna Andreadi | W2235: =IFERROR(INDEX(Returns!A:A,MATCH(B2235,Returns!B:B,0)),"No") -> No
A2236: 2235 | B2236: CA-2019-104066 | C2236: 43804 | D2236: 43809 | E2236: Standard Class | F2236: QJ-19255 | G2236: Quincy Jones | H2236: Corporate | I2236: United States | J2236: Burlington | K2236: Vermont | M2236: East | N2236: TEC-AC-10001013 | O2236: Technology | P2236: Accessories | Q2236: Logitech ClearChat Comfort/USB Headset H390 | R2236: 205.03 | S2236: 7 | T2236: 0 | U2236: 67.6599 | V2236: =IF(M2236=People!$B$5,People!$A$5,IF(M2236=People!$B$4,People!$A$4,IF(M2236=People!$B$3,People!$A$3,IF(M2236=People!$B$2,People!$A$2,0)))) -> Chuck Magee | W2236: =IFERROR(INDEX(Returns!A:A,MATCH(B2236,Returns!B:B,0)),"No") -> No
A2237: 2236 | B2237: CA-2017-145849 | C2237: 42993 | D2237: 42995 | E2237: Second Class | F2237: CT-11995 | G2237: Carol Triggs | H2237: Consumer | I2237: United States | J2237: Indianapolis | K2237: Indiana | L2237: 46203 | M2237: Central | N2237: OFF-ST-10000025 | O2237: Office Supplies | P2237: Storage | Q2237: Fellowes Stor/Drawer Steel Plus Storage Drawers | R2237: 190.86 | S2237: 2 | T2237: 0 | U2237: 11.4516 | V2237: =IF(M2237=People!$B$5,People!$A$5,IF(M2237=People!$B$4,People!$A$4,IF(M2237=People!$B$3,People!$A$3,IF(M2237=People!$B$2,People!$A$2,0)))) -> Kelly Williams | W2237: =IFERROR(INDEX(Returns!A:A,MATCH(B2237,Returns!B:B,0)),"No") -> No
A2238: 2237 | B2238: CA-2017-145849 | C2238: 42993 | D2238: 42995 | E2238: Second Class | F2238: CT-11995 | G2238: Carol Triggs | H2238: Consumer | I2238: United States | J2238: Indianapolis | K2238: Indiana | L2238: 46203 | M2238: Central | N2238: OFF-AR-10000817 | O2238: Office Supplies | P2238: Art | Q2238: Manco Dry-Lighter Erasable Highlighter | R2238: 24.32 | S2238: 8 | T2238: 0 | U2238: 8.2688 | V2238: =IF(M2238=People!$B$5,People!$A$5,IF(M2238=People!$B$4,People!$A$4,IF(M2238=People!$B$3,People!$A$3,IF(M2238=People!$B$2,People!$A$2,0)))) -> Kelly Williams | W2238: =IFERROR(INDEX(Returns!A:A,MATCH(B2238,Returns!B:B,0)),"No") -> No
A2239: 2238 | B2239: CA-2018-122322 | C2239: 43296 | D2239: 43302 | E2239: Standard Class | F2239: RH-19510 | G2239: Rick Huthwaite | H2239: Home Office | I2239: United States | J2239: Provo | K2239: Utah | L2239: 84604 | M2239: West | N2239: OFF-SU-10000952 | O2239: Office Supplies | P2239: Supplies | Q2239: Fiskars Home & Office Scissors | R2239: 44.4 | S2239: 5 | T2239: 0 | U2239: 12.432 | V2239: =IF(M2239=People!$B$5,People!$A$5,IF(M2239=People!$B$4,People!$A$4,IF(M2239=People!$B$3,People!$A$3,IF(M2239=People!$B$2,People!$A$2,0)))) -> Anna Andreadi | W2239: =IFERROR(INDEX(Returns!A:A,MATCH(B2239,Returns!B:B,0)),"No") -> No
A2240: 2239 | B2240: CA-2019-166849 | C2240: 43575 | D2240: 43581 | E2240: Standard Class | F2240: SJ-20125 | G2240: Sanjit Jacobs | H2240: Home Office | I2240: United States | J2240: Chicago | K2240: Illinois | L2240: 60610 | M2240: Central | N2240: FUR-FU-10004597 | O2240: Furniture | P2240: Furnishings | Q2240: Eldon Cleatmat Chair Mats for Medium Pile Carpets | R2240: 44.4 | S2240: 2 | T2240: 0.6 | U2240: -52.17 | V2240: =IF(M2240=People!$B$5,People!$A$5,IF(M2240=People!$B$4,People!$A$4,IF(M2240=People!$B$3,People!$A$3,IF(M2240=People!$B$2,People!$A$2,0)))) -> Kelly Williams | W2240: =IFERROR(INDEX(Returns!A:A,MATCH(B2240,Returns!B:B,0)),"No") -> No
A2241: 2240 | B2241: CA-2018-146633 | C2241: 43419 | D2241: 43421 | E2241: Second Class | F2241: TG-21310 | G2241: Toby Gnade | H2241: Consumer | I2241: United States | J2241: Los Angeles | K2241: California | L2241: 90049 | M2241: West | N2241: OFF-BI-10003527 | O2241: Office Supplies | P2241: Binders | Q2241: Fellowes PB500 Electric Punch Plastic Comb Binding Machine with Manual Bind | R2241: 1016.792 | S2241: 1 | T2241: 0.2 | U2241: 381.297 | V2241: =IF(M2241=People!$B$5,People!$A$5,IF(M2241=People!$B$4,People!$A$4,IF(M2241=People!$B$3,People!$A$3,IF(M2241=People!$B$2,People!$A$2,0)))) -> Anna Andreadi | W2241: =IFERROR(INDEX(Returns!A:A,MATCH(B2241,Returns!B:B,0)),"No") -> No
A2242: 2241 | B2242: CA-2018-146633 | C2242: 43419 | D2242: 43421 | E2242: Second Class | F2242: TG-21310 | G2242: Toby Gnade | H2242: Consumer | I2242: United States | J2242: Los Angeles | K2242: California | L2242: 90049 | M2242: West | N2242: OFF-BI-10002982 | O2242: Office Supplies | P2242: Binders | Q2242: Avery Self-Adhesive Photo Pockets for Polaroid Photos | R2242: 38.136 | S2242: 7 | T2242: 0.2 | U2242: 13.3476 | V2242: =IF(M2242=People!$B$5,People!$A$5,IF(M2242=People!$B$4,People!$A$4,IF(M2242=People!$B$3,People!$A$3,IF(M2242=People!$B$2,People!$A$2,0)))) -> Anna Andreadi | W2242: =IFERROR(INDEX(Returns!A:A,MATCH(B2242,Returns!B:B,0)),"No") -> No
A2243: 2242 | B2243: US-2018-126893 | C2243: 43430 | D2243: 43435 | E2243: Standard Class | F2243: CT-11995 | G2243: Carol Triggs | H2243: Consumer | I2243: United States | J2243: Philadelphia | K2243: Pennsylvania | L2243: 19134 | M2243: East | N2243: TEC-PH-10004165 | O2243: Technology | P2243: Phones | Q2243: Mitel MiVoice 5330e IP Phone | R2243: 494.982 | S2243: 3 | T2243: 0.4 | U2243: -115.4958 | V2243: =IF(M2243=People!$B$5,People!$A$5,IF(M2243=People!$B$4,People!$A$4,IF(M2243=People!$B$3,People!$A$3,IF(M2243=People!$B$2,People!$A$2,0)))) -> Chuck Magee | W2243: =IFERROR(INDEX(Returns!A:A,MATCH(B2243,Returns!B:B,0)),"No") -> No
A2244: 2243 | B2244: CA-2019-103380 | C2244: 43790 | D2244: 43794 | E2244: Standard Class | F2244: BF-11005 | G2244: Barry Franz | H2244: Home Office | I2244: United States | J2244: Pasadena | K2244: California | L2244: 91104 | M2244: West | N2244: OFF-ST-10003442 | O2244: Office Supplies | P2244: Storage | Q2244: Eldon Portable Mobile Manager | R2244: 56.56 | S2244: 2 | T2244: 0 | U2244: 15.2712 | V2244: =IF(M2244=People!$B$5,People!$A$5,IF(M2244=People!$B$4,People!$A$4,IF(M2244=People!$B$3,People!$A$3,IF(M2244=People!$B$2,People!$A$2,0)))) -> Anna Andreadi | W2244: =IFERROR(INDEX(Returns!A:A,MATCH(B2244,Returns!B:B,0)),"No") -> Yes
A2245: 2244 | B2245: CA-2019-103380 | C2245: 43790 | D2245: 43794 | E2245: Standard Class | F2245: BF-11005 | G2245: Barry Franz | H2245: Home Office | I2245: United States | J2245: Pasadena | K2245: California | L2245: 91104 | M2245: West | N2245: OFF-AR-10003856 | O2245: Office Supplies | P2245: Art | Q2245: Newell 344 | R2245: 5.56 | S2245: 2 | T2245: 0 | U2245: 1.4456 | V2245: =IF(M2245=People!$B$5,People!$A$5,IF(M2245=People!$B$4,People!$A$4,IF(M2245=People!$B$3,People!$A$3,IF(M2245=People!$B$2,People!$A$2,0)))) -> Anna Andreadi | W2245: =IFERROR(INDEX(Returns!A:A,MATCH(B2245,Returns!B:B,0)),"No") -> Yes
A2246: 2245 | B2246: CA-2019-103380 | C2246: 43790 | D2246: 43794 | E2246: Standard Class | F2246: BF-11005 | G2246: Barry Franz | H2246: Home Office | I2246: United States | J2246: Pasadena | K2246: California | L2246: 91104 | M2246: West | N2246: OFF-FA-10004248 | O2246: Office Supplies | P2246: Fasteners | Q2246: Advantus T-Pin Paper Clips | R2246: 9.02 | S2246: 2 | T2246: 0 | U2246: 3.5178 | V2246: =IF(M2246=People!$B$5,People!$A$5,IF(M2246=People!$B$4,People!$A$4,IF(M2246=People!$B$3,People!$A$3,IF(M2246=People!$B$2,People!$A$2,0)))) -> Anna Andreadi | W2246: =IFERROR(INDEX(Returns!A:A,MATCH(B2246,Returns!B:B,0)),"No") -> Yes
A2247: 2246 | B2247: CA-2019-103380 | C2247: 43790 | D2247: 43794 | E2247: Standard Class | F2247: BF-11005 | G2247: Barry Franz | H2247: Home Office | I2247: United States | J2247: Pasadena | K2247: California | L2247: 91104 | M2247: West | N2247: OFF-AP-10001492 | O2247: Office Supplies | P2247: Appliances | Q2247: Acco Six-Outlet Power Strip, 4' Cord Length | R2247: 8.62 | S2247: 1 | T2247: 0 | U2247: 2.2412 | V2247: =IF(M2247=People!$B$5,People!$A$5,IF(M2247=People!$B$4,People!$A$4,IF(M2247=People!$B$3,People!$A$3,IF(M2247=People!$B$2,People!$A$2,0)))) -> Anna Andreadi | W2247: =IFERROR(INDEX(Returns!A:A,MATCH(B2247,Returns!B:B,0)),"No") -> Yes
A2248: 2247 | B2248: CA-2019-103380 | C2248: 43790 | D2248: 43794 | E2248: Standard Class | F2248: BF-11005 | G2248: Barry Franz | H2248: Home Office | I2248: United States | J2248: Pasadena | K2248: California | L2248: 91104 | M2248: West | N2248: TEC-PH-10004165 | O2248: Technology | P2248: Phones | Q2248: Mitel MiVoice 5330e IP Phone | R2248: 659.976 | S2248: 3 | T2248: 0.2 | U2248: 49.4982 | V2248: =IF(M2248=People!$B$5,People!$A$5,IF(M2248=People!$B$4,People!$A$4,IF(M2248=People!$B$3,People!$A$3,IF(M2248=People!$B$2,People!$A$2,0)))) -> Anna Andreadi | W2248: =IFERROR(INDEX(Returns!A:A,MATCH(B2248,Returns!B:B,0)),"No") -> Yes
... A5275: 5274 | B5275: US-2018-158309 | C5275: 43430 | D5275: 43433 | E5275: First Class | F5275: PA-19060 | G5275: Pete Armstrong | H5275: Home Office | I5275: United States | J5275: Miami | K5275: Florida | L5275: 33142 | M5275: South | N5275: OFF-BI-10000145 | O5275: Office Supplies | P5275: Binders | Q5275: Zipper Ring Binder Pockets | R5275: 3.744 | S5275: 4 | T5275: 0.7 | U5275: -2.6208 | V5275: =IF(M5275=People!$B$5,People!$A$5,IF(M5275=People!$B$4,People!$A$4,IF(M5275=People!$B$3,People!$A$3,IF(M5275=People!$B$2,People!$A$2,0)))) -> Cassandra Brandow | W5275: =IFERROR(INDEX(Returns!A:A,MATCH(B5275,Returns!B:B,0)),"No") -> No
A5276: 5275 | B5276: CA-2017-162887 | C5276: 43046 | D5276: 43048 | E5276: Second Class | F5276: SV-20785 | G5276: Stewart Visinsky | H5276: Consumer | I5276: United States | J5276: Burlington | K5276: Vermont | M5276: East | N5276: FUR-CH-10000595 | O5276: Furniture | P5276: Chairs | Q5276: Safco Contoured Stacking Chairs | R5276: 715.2 | S5276: 3 | T5276: 0 | U5276: 178.8 | V5276: =IF(M5276=People!$B$5,People!$A$5,IF(M5276=People!$B$4,People!$A$4,IF(M5276=People!$B$3,People!$A$3,IF(M5276=People!$B$2,People!$A$2,0)))) -> Chuck Magee | W5276: =IFERROR(INDEX(Returns!A:A,MATCH(B5276,Returns!B:B,0)),"No") -> No
A5277: 5276 | B5277: CA-2019-147333 | C5277: 43813 | D5277: 43819 | E5277: Standard Class | F5277: KL-16555 | G5277: Kelly Lampkin | H5277: Corporate | I5277: United States | J5277: Fayetteville | K5277: Arkansas | L5277: 72701 | M5277: South | N5277: TEC-AC-10004469 | O5277: Technology | P5277: Accessories | Q5277: Microsoft Sculpt Comfort Mouse | R5277: 159.8 | S5277: 4 | T5277: 0 | U5277: 70.312 | V5277: =IF(M5277=People!$B$5,People!$A$5,IF(M5277=People!$B$4,People!$A$4,IF(M5277=People!$B$3,People!$A$3,IF(M5277=People!$B$2,People!$A$2,0)))) -> Cassandra Brandow | W5277: =IFERROR(INDEX(Returns!A:A,MATCH(B5277,Returns!B:B,0)),"No") -> No
A5278: 5277 | B5278: CA-2019-147333 | C5278: 43813 | D5278: 43819 | E5278: Standard Class | F5278: KL-16555 | G5278: Kelly Lampkin | H5278: Corporate | I5278: United States | J5278: Fayetteville | K5278: Arkansas | L5278: 72701 | M5278: South | N5278: TEC-AC-10003038 | O5278: Technology | P5278: Accessories | Q5278: Kingston Digital DataTraveler 16GB USB 2.0 | R5278: 44.75 | S5278: 5 | T5278: 0 | U5278: 8.5025 | V5278: =IF(M5278=People!$B$5,People!$A$5,IF(M5278=People!$B$4,People!$A$4,IF(M5278=People!$B$3,People!$A$3,IF(M5278=People!$B$2,People!$A$2,0)))) -> Cassandra Brandow | W5278: =IFERROR(INDEX(Returns!A:A,MATCH(B5278,Returns!B:B,0)),"No") -> No
A5279: 5278 | B5279: CA-2016-113859 | C5279: 42626 | D5279: 42630 | E5279: Standard Class | F5279: BC-11125 | G5279: Becky Castell | H5279: Home Office | I5279: United States | J5279: Odessa | K5279: Texas | L5279: 79762 | M5279: Central | N5279: FUR-CH-10004698 | O5279: Furniture | P5279: Chairs | Q5279: Padded Folding Chairs, Black, 4/Carton | R5279: 340.116 | S5279: 6 | T5279: 0.3 | U5279: -9.7176 | V5279: =IF(M5279=People!$B$5,People!$A$5,IF(M5279=People!$B$4,People!$A$4,IF(M5279=People!$B$3,People!$A$3,IF(M5279=People!$B$2,People!$A$2,0)))) -> Kelly Williams | W5279: =IFERROR(INDEX(Returns!A:A,MATCH(B5279,Returns!B:B,0)),"No") -> No
A5280: 5279 | B5280: CA-2016-159681 | C5280: 42711 | D5280: 42717 | E5280: Standard Class | F5280: PO-18850 | G5280: Patrick O'Brill | H5280: Consumer | I5280: United States | J5280: Virginia Beach | K5280: Virginia | L5280: 23464 | M5280: South | N5280: OFF-PA-10003641 | O5280: Office Supplies | P5280: Paper | Q5280: Xerox 1909 | R5280: 105.52 | S5280: 4 | T5280: 0 | U5280: 48.5392 | V5280: =IF(M5280=People!$B$5,People!$A$5,IF(M5280=People!$B$4,People!$A$4,IF(M5280=People!$B$3,People!$A$3,IF(M5280=People!$B$2,People!$A$2,0)))) -> Cassandra Brandow | W5280: =IFERROR(INDEX(Returns!A:A,MATCH(B5280,Returns!B:B,0)),"No") -> No
A5281: 5280 | B5281: US-2019-104094 | C5281: 43715 | D5281: 43719 | E5281: Standard Class | F5281: AG-10675 | G5281: Anna Gayman | H5281: Consumer | I5281: United States | J5281: Milwaukee | K5281: Wisconsin | L5281: 53209 | M5281: Central | N5281: TEC-AC-10002134 | O5281: Technology | P5281: Accessories | Q5281: Rosewill 107 Normal Keys USB Wired Standard Keyboard | R5281: 13.48 | S5281: 1 | T5281: 0 | U5281: 1.8872 | V5281: =IF(M5281=People!$B$5,People!$A$5,IF(M5281=People!$B$4,People!$A$4,IF(M5281=People!$B$3,People!$A$3,IF(M5281=People!$B$2,People!$A$2,0)))) -> Kelly Williams | W5281: =IFERROR(INDEX(Returns!A:A,MATCH(B5281,Returns!B:B,0)),"No") -> No
A5282: 5281 | B5282: CA-2019-152709 | C5282: 43745 | D5282: 43750 | E5282: Standard Class | F5282: DB-13210 | G5282: Dean Braden | H5282: Consumer | I5282: United States | J5282: Detroit | K5282: Michigan | L5282: 48234 | M5282: Central | N5282: OFF-ST-10001837 | O5282: Office Supplies | P5282: Storage | Q5282: SAFCO Mobile Desk Side File, Wire Frame | R5282: 85.52 | S5282: 2 | T5282: 0 | U5282: 22.2352 | V5282: =IF(M5282=People!$B$5,People!$A$5,IF(M5282=People!$B$4,People!$A$4,IF(M5282=People!$B$3,People!$A$3,IF(M5282=People!$B$2,People!$A$2,0)))) -> Kelly Williams | W5282: =IFERROR(INDEX(Returns!A:A,MATCH(B5282,Returns!B:B,0)),"No") -> No
A5283: 5282 | B5283: CA-2017-105158 | C5283: 42983 | D5283: 42988 | E5283: Standard Class | F5283: SP-20860 | G5283: Sung Pak | H5283: Corporate | I5283: United States | J5283: Rochester | K5283: Minnesota | L5283: 55901 | M5283: Central | N5283: FUR-FU-10001706 | O5283: Furniture | P5283: Furnishings | Q5283: Longer-Life Soft White Bulbs | R5283: 6.16 | S5283: 2 | T5283: 0 | U5283: 2.9568 | V5283: =IF(M5283=People!$B$5,People!$A$5,IF(M5283=People!$B$4,People!$A$4,IF(M5283=People!$B$3,People!$A$3,IF(M5283=People!$B$2,People!$A$2,0)))) -> Kelly Williams | W5283: =IFERROR(INDEX(Returns!A:A,MATCH(B5283,Returns!B:B,0)),"No") -> Yes
A5284: 5283 | B5284: CA-2017-105158 | C5284: 42983 | D5284: 42988 | E5284: Standard Class | F5284: SP-20860 | G5284: Sung Pak | H5284: Corporate | I5284: United States | J5284: Rochester | K5284: Minnesota | L5284: 55901 | M5284: Central | N5284: OFF-PA-10001970 | O5284: Office Supplies | P5284: Paper | Q5284: Xerox 1881 | R5284: 36.84 | S5284: 3 | T5284: 0 | U5284: 17.3148 | V5284: =IF(M5284=People!$B$5,People!$A$5,IF(M5284=People!$B$4,People!$A$4,IF(M5284=People!$B$3,People!$A$3,IF(M5284=People!$B$2,People!$A$2,0)))) -> Kelly Williams | W5284: =IFERROR(INDEX(Returns!A:A,MATCH(B5284,Returns!B:B,0)),"No") -> Yes
A5285: 5284 | B5285: CA-2016-133424 | C5285: 42459 | D5285: 42464 | E5285: Standard Class | F5285: Dl-13600 | G5285: Dorris liebe | H5285: Corporate | I5285: United States | J5285: Seattle | K5285: Washington | L5285: 98105 | M5285: West | N5285: OFF-ST-10002957 | O5285: Office Supplies | P5285: Storage | Q5285: Sterilite Show Offs Storage Containers | R5285: 15.84 | S5285: 3 | T5285: 0 | U5285: 0 | V5285: =IF(M5285=People!$B$5,People!$A$5,IF(M5285=People!$B$4,People!$A$4,IF(M5285=People!$B$3,People!$A$3,IF(M5285=People!$B$2,People!$A$2,0)))) -> Anna Andreadi | W5285: =IFERROR(INDEX(Returns!A:A,MATCH(B5285,Returns!B:B,0)),"No") -> No
A5286: 5285 | B5286: CA-2016-133424 | C5286: 42459 | D5286: 42464 | E5286: Standard Class | F5286: Dl-13600 | G5286: Dorris liebe | H5286: Corporate | I5286: United States | J5286: Seattle | K5286: Washington | L5286: 98105 | M5286: West | N5286: OFF-LA-10002312 | O5286: Office Supplies | P5286: Labels | Q5286: Avery 490 | R5286: 44.4 | S5286: 3 | T5286: 0 | U5286: 22.2 | V5286: =IF(M5286=People!$B$5,People!$A$5,IF(M5286=People!$B$4,People!$A$4,IF(M5286=People!$B$3,People!$A$3,IF(M5286=People!$B$2,People!$A$2,0)))) -> Anna Andreadi | W5286: =IFERROR(INDEX(Returns!A:A,MATCH(B5286,Returns!B:B,0)),"No") -> No
A5287: 5286 | B5287: CA-2019-105991 | C5287: 43590 | D5287: 43591 | E5287: First Class | F5287: LH-17020 | G5287: Lisa Hazard | H5287: Consumer | I5287: United States | J5287: Louisville | K5287: Colorado | L5287: 80027 | M5287: West | N5287: OFF-EN-10002600 | O5287: Office Supplies | P5287: Envelopes | Q5287: Redi-Strip #10 Envelopes, 4 1/8 x 9 1/2 | R5287: 21.24 | S5287: 9 | T5287: 0.2 | U5287: 7.434 | V5287: =IF(M5287=People!$B$5,People!$A$5,IF(M5287=People!$B$4,People!$A$4,IF(M5287=People!$B$3,People!$A$3,IF(M5287=People!$B$2,People!$A$2,0)))) -> Anna Andreadi | W5287: =IFERROR(INDEX(Returns!A:A,MATCH(B5287,Returns!B:B,0)),"No") -> No
A5288: 5287 | B5288: CA-2019-105991 | C5288: 43590 | D5288: 43591 | E5288: First Class | F5288: LH-17020 | G5288: Lisa Hazard | H5288: Consumer | I5288: United States | J5288: Louisville | K5288: Colorado | L5288: 80027 | M5288: West | N5288: OFF-BI-10003274 | O5288: Office Supplies | P5288: Binders | Q5288: Avery Durable Slant Ring Binders, No Labels | R5288: 9.552 | S5288: 8 | T5288: 0.7 | U5288: -7.3232 | V5288: =IF(M5288=People!$B$5,People!$A$5,IF(M5288=People!$B$4,People!$A$4,IF(M5288=People!$B$3,People!$A$3,IF(M5288=People!$B$2,People!$A$2,0)))) -> Anna Andreadi | W5288: =IFERROR(INDEX(Returns!A:A,MATCH(B5288,Returns!B:B,0)),"No") -> No
... A8799: 8798 | B8799: CA-2018-106397 | C8799: 43288 | D8799: 43294 | E8799: Standard Class | F8799: MJ-17740 | G8799: Max Jones | H8799: Consumer | I8799: United States | J8799: Orem | K8799: Utah | L8799: 84057 | M8799: West | N8799: OFF-AR-10004602 | O8799: Office Supplies | P8799: Art | Q8799: Boston KS Multi-Size Manual Pencil Sharpener | R8799: 45.98 | S8799: 2 | T8799: 0 | U8799: 12.8744 | V8799: =IF(M8799=People!$B$5,People!$A$5,IF(M8799=People!$B$4,People!$A$4,IF(M8799=People!$B$3,People!$A$3,IF(M8799=People!$B$2,People!$A$2,0)))) -> Anna Andreadi | W8799: =IFERROR(INDEX(Returns!A:A,MATCH(B8799,Returns!B:B,0)),"No") -> No
A8800: 8799 | B8800: US-2018-150140 | C8800: 43196 | D8800: 43200 | E8800: Standard Class | F8800: VM-21685 | G8800: Valerie Mitchum | H8800: Home Office | I8800: United States | J8800: Burlington | K8800: Vermont | M8800: East | N8800: TEC-PH-10002555 | O8800: Technology | P8800: Phones | Q8800: Nortel Meridian M5316 Digital phone | R8800: 1294.75 | S8800: 5 | T8800: 0 | U8800: 336.635 | V8800: =IF(M8800=People!$B$5,People!$A$5,IF(M8800=People!$B$4,People!$A$4,IF(M8800=People!$B$3,People!$A$3,IF(M8800=People!$B$2,People!$A$2,0)))) -> Chuck Magee | W8800: =IFERROR(INDEX(Returns!A:A,MATCH(B8800,Returns!B:B,0)),"No") -> No
A8801: 8800 | B8801: CA-2016-116666 | C8801: 42498 | D8801: 42500 | E8801: First Class | F8801: KT-16480 | G8801: Kean Thornton | H8801: Consumer | I8801: United States | J8801: Philadelphia | K8801: Pennsylvania | L8801: 19134 | M8801: East | N8801: TEC-CO-10001449 | O8801: Technology | P8801: Copiers | Q8801: Hewlett Packard LaserJet 3310 Copier | R8801: 1799.97 | S8801: 5 | T8801: 0.4 | U8801: 239.996 | V8801: =IF(M8801=People!$B$5,People!$A$5,IF(M8801=People!$B$4,People!$A$4,IF(M8801=People!$B$3,People!$A$3,IF(M8801=People!$B$2,People!$A$2,0)))) -> Chuck Magee | W8801: =IFERROR(INDEX(Returns!A:A,MATCH(B8801,Returns!B:B,0)),"No") -> No
A8802: 8801 | B8802: CA-2019-148992 | C8802: 43792 | D8802: 43796 | E8802: Standard Class | F8802: CS-12250 | G8802: Chris Selesnick | H8802: Corporate | I8802: United States | J8802: Chicago | K8802: Illinois | L8802: 60623 | M8802: Central | N8802: OFF-PA-10004285 | O8802: Office Supplies | P8802: Paper | Q8802: Xerox 1959 | R8802: 10.688 | S8802: 2 | T8802: 0.2 | U8802: 3.7408 | V8802: =IF(M8802=People!$B$5,People!$A$5,IF(M8802=People!$B$4,People!$A$4,IF(M8802=People!$B$3,People!$A$3,IF(M8802=People!$B$2,People!$A$2,0)))) -> Kelly Williams | W8802: =IFERROR(INDEX(Returns!A:A,MATCH(B8802,Returns!B:B,0)),"No") -> No
A8803: 8802 | B8803: CA-2018-140935 | C8803: 43414 | D8803: 43416 | E8803: First Class | F8803: AB-10015 | G8803: Aaron Bergman | H8803: Consumer | I8803: United States | J8803: Oklahoma City | K8803: Oklahoma | L8803: 73120 | M8803: Central | N8803: TEC-PH-10000562 | O8803: Technology | P8803: Phones | Q8803: Samsung Convoy 3 | R8803: 221.98 | S8803: 2 | T8803: 0 | U8803: 62.1544 | V8803: =IF(M8803=People!$B$5,People!$A$5,IF(M8803=People!$B$4,People!$A$4,IF(M8803=People!$B$3,People!$A$3,IF(M8803=People!$B$2,People!$A$2,0)))) -> Kelly Williams | W8803: =IFERROR(INDEX(Returns!A:A,MATCH(B8803,Returns!B:B,0)),"No") -> No
A8804: 8803 | B8804: CA-2018-140935 | C8804: 43414 | D8804: 43416 | E8804: First Class | F8804: AB-10015 | G8804: Aaron Bergman | H8804: Consumer | I8804: United States | J8804: Oklahoma City | K8804: Oklahoma | L8804: 73120 | M8804: Central | N8804: FUR-BO-10003966 | O8804: Furniture | P8804: Bookcases | Q8804: Sauder Facets Collection Library, Sky Alder Finish | R8804: 341.96 | S8804: 2 | T8804: 0 | U8804: 54.7136 | V8804: =IF(M8804=People!$B$5,People!$A$5,IF(M8804=People!$B$4,People!$A$4,IF(M8804=People!$B$3,People!$A$3,IF(M8804=People!$B$2,People!$A$2,0)))) -> Kelly Williams | W8804: =IFERROR(INDEX(Returns!A:A,MATCH(B8804,Returns!B:B,0)),"No") -> No
A8805: 8804 | B8805: CA-2016-157644 | C8805: 42735 | D8805: 42736 | E8805: First Class | F8805: AH-10030 | G8805: Aaron Hawkins | H8805: Corporate | I8805: United States | J8805: New York City | K8805: New York | L8805: 10035 | M8805: East | N8805: TEC-AC-10003614 | O8805: Technology | P8805: Accessories | Q8805: Verbatim 25 GB 6x Blu-ray Single Layer Recordable Disc, 10/Pack | R8805: 34.77 | S8805: 3 | T8805: 0 | U8805: 11.4741 | V8805: =IF(M8805=People!$B$5,People!$A$5,IF(M8805=People!$B$4,People!$A$4,IF(M8805=People!$B$3,People!$A$3,IF(M8805=People!$B$2,People!$A$2,0)))) -> Chuck Magee | W8805: =IFERROR(INDEX(Returns!A:A,MATCH(B8805,Returns!B:B,0)),"No") -> No
A8806: 8805 | B8806: CA-2016-157644 | C8806: 42735 | D8806: 42736 | E8806: First Class | F8806: AH-10030 | G8806: Aaron Hawkins | H8806: Corporate | I8806: United States | J8806: New York City | K8806: New York | L8806: 10035 | M8806: East | N8806: OFF-LA-10003148 | O8806: Office Supplies | P8806: Labels | Q8806: Avery 51 | R8806: 18.9 | S8806: 3 | T8806: 0 | U8806: 8.694 | V8806: =IF(M8806=People!$B$5,People!$A$5,IF(M8806=People!$B$4,People!$A$4,IF(M8806=People!$B$3,People!$A$3,IF(M8806=People!$B$2,People!$A$2,0)))) -> Chuck Magee | W8806: =IFERROR(INDEX(Returns!A:A,MATCH(B8806,Returns!B:B,0)),"No") -> No
A8807: 8806 | B8807: US-2019-100398 | C8807: 43696 | D8807: 43700 | E8807: Standard Class | F8807: DO-13435 | G8807: Denny Ordway | H8807: Consumer | I8807: United States | J8807: Salt Lake City | K8807: Utah | L8807: 84106 | M8807: West | N8807: OFF-BI-10002133 | O8807: Office Supplies | P8807: Binders | Q8807: Wilson Jones Elliptical Ring 3 1/2" Capacity Binders, 800 sheets | R8807: 102.72 | S8807: 3 | T8807: 0.2 | U8807: 37.236 | V8807: =IF(M8807=People!$B$5,People!$A$5,IF(M8807=People!$B$4,People!$A$4,IF(M8807=People!$B$3,People!$A$3,IF(M8807=People!$B$2,People!$A$2,0)))) -> Anna Andreadi | W8807: =IFERROR(INDEX(Returns!A:A,MATCH(B8807,Returns!B:B,0)),"No") -> No
A8808: 8807 | B8808: CA-2018-113082 | C8808: 43355 | D8808: 43359 | E8808: Standard Class | F8808: MC-17590 | G8808: Matt Collister | H8808: Corporate | I8808: United States | J8808: Utica | K8808: New York | L8808: 13501 | M8808: East | N8808: FUR-FU-10002813 | O8808: Furniture | P8808: Furnishings | Q8808: DAX Contemporary Wood Frame with Silver Metal Mat, Desktop, 11 x 14 Size | R8808: 40.48 | S8808: 2 | T8808: 0 | U8808: 14.5728 | V8808: =IF(M8808=People!$B$5,People!$A$5,IF(M8808=People!$B$4,People!$A$4,IF(M8808=People!$B$3,People!$A$3,IF(M8808=People!$B$2,People!$A$2,0)))) -> Chuck Magee | W8808: =IFERROR(INDEX(Returns!A:A,MATCH(B8808,Returns!B:B,0)),"No") -> No
A8809: 8808 | B8809: US-2019-110646 | C8809: 43764 | D8809: 43769 | E8809: Standard Class | F8809: JF-15190 | G8809: Jamie Frazer | H8809: Consumer | I8809: United States | J8809: Philadelphia | K8809: Pennsylvania | L8809: 19134 | M8809: East | N8809: OFF-BI-10004330 | O8809: Office Supplies | P8809: Binders | Q8809: GBC Velobind Prepunched Cover Sets, Regency Series | R8809: 33.282 | S8809: 3 | T8809: 0.7 | U8809: -27.735 | V8809: =IF(M8809=People!$B$5,People!$A$5,IF(M8809=People!$B$4,People!$A$4,IF(M8809=People!$B$3,People!$A$3,IF(M8809=People!$B$2,People!$A$2,0)))) -> Chuck Magee | W8809: =IFERROR(INDEX(Returns!A:A,MATCH(B8809,Returns!B:B,0)),"No") -> No
A8810: 8809 | B8810: US-2019-110646 | C8810: 43764 | D8810: 43769 | E8810: Standard Class | F8810: JF-15190 | G8810: Jamie Frazer | H8810: Consumer | I8810: United States | J8810: Philadelphia | K8810: Pennsylvania | L8810: 19134 | M8810: East | N8810: TEC-PH-10002807 | O8810: Technology | P8810: Phones | Q8810: Motorla HX550 Universal Bluetooth Headset | R8810: 118.65 | S8810: 5 | T8810: 0.4 | U8810: 19.775 | V8810: =IF(M8810=People!$B$5,People!$A$5,IF(M8810=People!$B$4,People!$A$4,IF(M8810=People!$B$3,People!$A$3,IF(M8810=People!$B$2,People!$A$2,0)))) -> Chuck Magee | W8810: =IFERROR(INDEX(Returns!A:A,MATCH(B8810,Returns!B:B,0)),"No") -> No
A8811: 8810 | B8811: US-2019-110646 | C8811: 43764 | D8811: 43769 | E8811: Standard Class | F8811: JF-15190 | G8811: Jamie Frazer | H8811: Consumer | I8811: United States | J8811: Philadelphia | K8811: Pennsylvania | L8811: 19134 | M8811: East | N8811: OFF-LA-10001404 | O8811: Office Supplies | P8811: Labels | Q8811: Avery 517 | R8811: 14.76 | S8811: 5 | T8811: 0.2 | U8811: 4.9815 | V8811: =IF(M8811=People!$B$5,People!$A$5,IF(M8811=People!$B$4,People!$A$4,IF(M8811=People!$B$3,People!$A$3,IF(M8811=People!$B$2,People!$A$2,0)))) -> Chuck Magee | W8811: =IFERROR(INDEX(Returns!A:A,MATCH(B8811,Returns!B:B,0)),"No") -> No
A8812: 8811 | B8812: CA-2019-120614 | C8812: 43615 | D8812: 43620 | E8812: Standard Class | F8812: SM-20950 | G8812: Suzanne McNair | H8812: Corporate | I8812: United States | J8812: Los Angeles | K8812: California | L8812: 90004 | M8812: West | N8812: OFF-PA-10004911 | O8812: Office Supplies | P8812: Paper | Q8812: Rediform S.O.S. 1-Up Phone Message Bk, 4-1/4x3-1/16 Bk, 1 Form/Pg, 40 Messages/Bk, 3/Pk | R8812: 37.52 | S8812: 4 | T8812: 0 | U8812: 18.0096 | V8812: =IF(M8812=People!$B$5,People!$A$5,IF(M8812=People!$B$4,People!$A$4,IF(M8812=People!$B$3,People!$A$3,IF(M8812=People!$B$2,People!$A$2,0)))) -> Anna Andreadi | W8812: =IFERROR(INDEX(Returns!A:A,MATCH(B8812,Returns!B:B,0)),"No") -> No
... A9147: 9146 | B9147: CA-2017-126970 | C9147: 42998 | D9147: 43002 | E9147: Standard Class | F9147: TP-21130 | G9147: Theone Pippenger | H9147: Consumer | I9147: United States | J9147: Naperville | K9147: Illinois | L9147: 60540 | M9147: Central | N9147: OFF-BI-10000138 | O9147: Office Supplies | P9147: Binders | Q9147: Acco Translucent Poly Ring Binders | R9147: 2.808 | S9147: 3 | T9147: 0.8 | U9147: -4.4928 | V9147: =IF(M9147=People!$B$5,People!$A$5,IF(M9147=People!$B$4,People!$A$4,IF(M9147=People!$B$3,People!$A$3,IF(M9147=People!$B$2,People!$A$2,0)))) -> Kelly Williams | W9147: =IFERROR(INDEX(Returns!A:A,MATCH(B9147,Returns!B:B,0)),"No") -> No
A9148: 9147 | B9148: US-2018-165505 | C9148: 43123 | D9148: 43127 | E9148: Standard Class | F9148: CB-12535 | G9148: Claudia Bergmann | H9148: Corporate | I9148: United States | J9148: Burlington | K9148: Vermont | M9148: East | N9148: TEC-AC-10002926 | O9148: Technology | P9148: Accessories | Q9148: Logitech Wireless Marathon Mouse M705 | R9148: 99.98 | S9148: 2 | T9148: 0 | U9148: 42.9914 | V9148: =IF(M9148=People!$B$5,People!$A$5,IF(M9148=People!$B$4,People!$A$4,IF(M9148=People!$B$3,People!$A$3,IF(M9148=People!$B$2,People!$A$2,0)))) -> Chuck Magee | W9148: =IFERROR(INDEX(Returns!A:A,MATCH(B9148,Returns!B:B,0)),"No") -> No
A9149: 9148 | B9149: US-2018-165505 | C9149: 43123 | D9149: 43127 | E9149: Standard Class | F9149: CB-12535 | G9149: Claudia Bergmann | H9149: Corporate | I9149: United States | J9149: Burlington | K9149: Vermont | M9149: East | N9149: OFF-AR-10003477 | O9149: Office Supplies | P9149: Art | Q9149: 4009 Highlighters | R9149: 8.04 | S9149: 6 | T9149: 0 | U9149: 2.7336 | V9149: =IF(M9149=People!$B$5,People!$A$5,IF(M9149=People!$B$4,People!$A$4,IF(M9149=People!$B$3,People!$A$3,IF(M9149=People!$B$2,People!$A$2,0)))) -> Chuck Magee | W9149: =IFERROR(INDEX(Returns!A:A,MATCH(B9149,Returns!B:B,0)),"No") -> No
A9150: 9149 | B9150: US-2018-165505 | C9150: 43123 | D9150: 43127 | E9150: Standard Class | F9150: CB-12535 | G9150: Claudia Bergmann | H9150: Corporate | I9150: United States | J9150: Burlington | K9150: Vermont | M9150: East | N9150: OFF-ST-10001526 | O9150: Office Supplies | P9150: Storage | Q9150: Iceberg Mobile Mega Data/Printer Cart | R9150: 1564.29 | S9150: 13 | T9150: 0 | U9150: 406.7154 | V9150: =IF(M9150=People!$B$5,People!$A$5,IF(M9150=People!$B$4,People!$A$4,IF(M9150=People!$B$3,People!$A$3,IF(M9150=People!$B$2,People!$A$2,0)))) -> Chuck Magee | W9150: =IFERROR(INDEX(Returns!A:A,MATCH(B9150,Returns!B:B,0)),"No") -> No
A9151: 9150 | B9151: US-2016-157070 | C9151: 42522 | D9151: 42527 | E9151: Standard Class | F9151: QJ-19255 | G9151: Quincy Jones | H9151: Corporate | I9151: United States | J9151: Detroit | K9151: Michigan | L9151: 48234 | M9151: Central | N9151: OFF-BI-10001765 | O9151: Office Supplies | P9151: Binders | Q9151: Wilson Jones Heavy-Duty Casebound Ring Binders with Metal Hinges | R9151: 138.56 | S9151: 4 | T9151: 0 | U9151: 66.5088 | V9151: =IF(M9151=People!$B$5,People!$A$5,IF(M9151=People!$B$4,People!$A$4,IF(M9151=People!$B$3,People!$A$3,IF(M9151=People!$B$2,People!$A$2,0)))) -> Kelly Williams | W9151: =IFERROR(INDEX(Returns!A:A,MATCH(B9151,Returns!B:B,0)),"No") -> No
A9152: 9151 | B9152: US-2016-157070 | C9152: 42522 | D9152: 42527 | E9152: Standard Class | F9152: QJ-19255 | G9152: Quincy Jones | H9152: Corporate | I9152: United States | J9152: Detroit | K9152: Michigan | L9152: 48234 | M9152: Central | N9152: OFF-AP-10004859 | O9152: Office Supplies | P9152: Appliances | Q9152: Acco 6 Outlet Guardian Premium Surge Suppressor | R9152: 65.52 | S9152: 5 | T9152: 0.1 | U9152: 12.376 | V9152: =IF(M9152=People!$B$5,People!$A$5,IF(M9152=People!$B$4,People!$A$4,IF(M9152=People!$B$3,People!$A$3,IF(M9152=People!$B$2,People!$A$2,0)))) -> Kelly Williams | W9152: =IFERROR(INDEX(Returns!A:A,MATCH(B9152,Returns!B:B,0)),"No") -> No
A9153: 9152 | B9153: US-2017-106873 | C9153: 43002 | D9153: 43007 | E9153: Second Class | F9153: KM-16720 | G9153: Kunst Miller | H9153: Consumer | I9153: United States | J9153: Avondale | K9153: Arizona | L9153: 85323 | M9153: West | N9153: OFF-AR-10003179 | O9153: Office Supplies | P9153: Art | Q9153: Dixon Ticonderoga Core-Lock Colored Pencils | R9153: 14.576 | S9153: 2 | T9153: 0.2 | U9153: 2.3686 | V9153: =IF(M9153=People!$B$5,People!$A$5,IF(M9153=People!$B$4,People!$A$4,IF(M9153=People!$B$3,People!$A$3,IF(M9153=People!$B$2,People!$A$2,0)))) -> Anna Andreadi | W9153: =IFERROR(INDEX(Returns!A:A,MATCH(B9153,Returns!B:B,0)),"No") -> No
A9154: 9153 | B9154: US-2017-106873 | C9154: 43002 | D9154: 43007 | E9154: Second Class | F9154: KM-16720 | G9154: Kunst Miller | H9154: Consumer | I9154: United States | J9154: Avondale | K9154: Arizona | L9154: 85323 | M9154: West | N9154: TEC-AC-10002345 | O9154: Technology | P9154: Accessories | Q9154: HP Standard 104 key PS/2 Keyboard | R9154: 23.2 | S9154: 2 | T9154: 0.2 | U9154: 1.45 | V9154: =IF(M9154=People!$B$5,People!$A$5,IF(M9154=People!$B$4,People!$A$4,IF(M9154=People!$B$3,People!$A$3,IF(M9154=People!$B$2,People!$A$2,0)))) -> Anna Andreadi | W9154: =IFERROR(INDEX(Returns!A:A,MATCH(B9154,Returns!B:B,0)),"No") -> No
A9155: 9154 | B9155: US-2017-106873 | C9155: 43002 | D9155: 43007 | E9155: Second Class | F9155: KM-16720 | G9155: Kunst Miller | H9155: Consumer | I9155: United States | J9155: Avondale | K9155: Arizona | L9155: 85323 | M9155: West | N9155: OFF-AR-10001246 | O9155: Office Supplies | P9155: Art | Q9155: Newell 317 | R9155: 16.464 | S9155: 7 | T9155: 0.2 | U9155: 1.8522 | V9155: =IF(M9155=People!$B$5,People!$A$5,IF(M9155=People!$B$4,People!$A$4,IF(M9155=People!$B$3,People!$A$3,IF(M9155=People!$B$2,People!$A$2,0)))) -> Anna Andreadi | W9155: =IFERROR(INDEX(Returns!A:A,MATCH(B9155,Returns!B:B,0)),"No") -> No
A9156: 9155 | B9156: CA-2018-132990 | C9156: 43313 | D9156: 43315 | E9156: Second Class | F9156: KM-16660 | G9156: Khloe Miller | H9156: Consumer | I9156: United States | J9156: Philadelphia | K9156: Pennsylvania | L9156: 19140 | M9156: East | N9156: FUR-FU-10004864 | O9156: Furniture | P9156: Furnishings | Q9156: Eldon 500 Class Desk Accessories | R9156: 19.312 | S9156: 2 | T9156: 0.2 | U9156: 3.1382 | V9156: =IF(M9156=People!$B$5,People!$A$5,IF(M9156=People!$B$4,People!$A$4,IF(M9156=People!$B$3,People!$A$3,IF(M9156=People!$B$2,People!$A$2,0)))) -> Chuck Magee | W9156: =IFERROR(INDEX(Returns!A:A,MATCH(B9156,Returns!B:B,0)),"No") -> No
A9157: 9156 | B9157: CA-2016-102645 | C9157: 42392 | D9157: 42397 | E9157: Standard Class | F9157: IM-15055 | G9157: Ionia McGrath | H9157: Consumer | I9157: United States | J9157: Las Vegas | K9157: Nevada | L9157: 89115 | M9157: West | N9157: OFF-PA-10001804 | O9157: Office Supplies | P9157: Paper | Q9157: Xerox 195 | R9157: 40.08 | S9157: 6 | T9157: 0 | U9157: 19.2384 | V9157: =IF(M9157=People!$B$5,People!$A$5,IF(M9157=People!$B$4,People!$A$4,IF(M9157=People!$B$3,People!$A$3,IF(M9157=People!$B$2,People!$A$2,0)))) -> Anna Andreadi | W9157: =IFERROR(INDEX(Returns!A:A,MATCH(B9157,Returns!B:B,0)),"No") -> No
A9158: 9157 | B9158: CA-2016-134215 | C9158: 42586 | D9158: 42590 | E9158: Standard Class | F9158: ML-17395 | G9158: Marina Lichtenstein | H9158: Corporate | I9158: United States | J9158: Bangor | K9158: Maine | L9158: 4401 | M9158: East | N9158: OFF-AP-10001271 | O9158: Office Supplies | P9158: Appliances | Q9158: Eureka The Boss Cordless Rechargeable Stick Vac | R9158: 101.96 | S9158: 2 | T9158: 0 | U9158: 27.5292 | V9158: =IF(M9158=People!$B$5,People!$A$5,IF(M9158=People!$B$4,People!$A$4,IF(M9158=People!$B$3,People!$A$3,IF(M9158=People!$B$2,People!$A$2,0)))) -> Chuck Magee | W9158: =IFERROR(INDEX(Returns!A:A,MATCH(B9158,Returns!B:B,0)),"No") -> No
A9159: 9158 | B9159: CA-2016-134215 | C9159: 42586 | D9159: 42590 | E9159: Standard Class | F9159: ML-17395 | G9159: Marina Lichtenstein | H9159: Corporate | I9159: United States | J9159: Bangor | K9159: Maine | L9159: 4401 | M9159: East | N9159: OFF-PA-10004353 | O9159: Office Supplies | P9159: Paper | Q9159: Southworth 25% Cotton Premium Laser Paper and Envelopes | R9159: 259.74 | S9159: 13 | T9159: 0 | U9159: 124.6752 | V9159: =IF(M9159=People!$B$5,People!$A$5,IF(M9159=People!$B$4,People!$A$4,IF(M9159=People!$B$3,People!$A$3,IF(M9159=People!$B$2,People!$A$2,0)))) -> Chuck Magee | W9159: =IFERROR(INDEX(Returns!A:A,MATCH(B9159,Returns!B:B,0)),"No") -> No
A9160: 9159 | B9160: CA-2016-134215 | C9160: 42586 | D9160: 42590 | E9160: Standard Class | F9160: ML-17395 | G9160: Marina Lichtenstein | H9160: Corporate | I9160: United States | J9160: Bangor | K9160: Maine | L9160: 4401 | M9160: East | N9160: TEC-AC-10002473 | O9160: Technology | P9160: Accessories | Q9160: Maxell 4.7GB DVD-R | R9160: 255.42 | S9160: 9 | T9160: 0 | U9160: 104.7222 | V9160: =IF(M9160=People!$B$5,People!$A$5,IF(M9160=People!$B$4,People!$A$4,IF(M9160=People!$B$3,People!$A$3,IF(M9160=People!$B$2,People!$A$2,0)))) -> Chuck Magee | W9160: =IFERROR(INDEX(Returns!A:A,MATCH(B9160,Returns!B:B,0)),"No") -> No
A9161: 9160 | B9161: CA-2018-118934 | C9161: 43321 | D9161: 43326 | E9161: Standard Class | F9161: GH-14410 | G9161: Gary Hansen | H9161: Home Office | I9161: United States | J9161: Hendersonville | K9161: Tennessee | L9161: 37075 | M9161: South | N9161: OFF-BI-10003314 | O9161: Office Supplies | P9161: Binders | Q9161: Tuff Stuff Recycled Round Ring Binders | R9161: 4.338 | S9161: 3 | T9161: 0.7 | U9161: -3.0366 | V9161: =IF(M9161=People!$B$5,People!$A$5,IF(M9161=People!$B$4,People!$A$4,IF(M9161=People!$B$3,People!$A$3,IF(M9161=People!$B$2,People!$A$2,0)))) -> Cassandra Brandow | W9161: =IFERROR(INDEX(Returns!A:A,MATCH(B9161,Returns!B:B,0)),"No") -> No
A9162: 9161 | B9162: CA-2018-118934 | C9162: 43321 | D9162: 43326 | E9162: Standard Class | F9162: GH-14410 | G9162: Gary Hansen | H9162: Home Office | I9162: United States | J9162: Hendersonville | K9162: Tennessee | L9162: 37075 | M9162: South | N9162: OFF-BI-10004465 | O9162: Office Supplies | P9162: Binders | Q9162: Avery Durable Slant Ring Binders | R9162: 11.88 | S9162: 5 | T9162: 0.7 | U9162: -7.92 | V9162: =IF(M9162=People!$B$5,People!$A$5,IF(M9162=People!$B$4,People!$A$4,IF(M9162=People!$B$3,People!$A$3,IF(M9162=People!$B$2,People!$A$2,0)))) -> Cassandra Brandow | W9162: =IFERROR(INDEX(Returns!A:A,MATCH(B9162,Returns!B:B,0)),"No") -> No
... A9387: 9386 | B9387: CA-2019-163097 | C9387: 43704 | D9387: 43708 | E9387: Standard Class | F9387: SF-20200 | G9387: Sarah Foster | H9387: Consumer | I9387: United States | J9387: Mesa | K9387: Arizona | L9387: 85204 | M9387: West | N9387: FUR-FU-10004973 | O9387: Furniture | P9387: Furnishings | Q9387: Flat Face Poster Frame | R9387: 120.576 | S9387: 8 | T9387: 0.2 | U9387: 33.1584 | V9387: =IF(M9387=People!$B$5,People!$A$5,IF(M9387=People!$B$4,People!$A$4,IF(M9387=People!$B$3,People!$A$3,IF(M9387=People!$B$2,People!$A$2,0)))) -> Anna Andreadi | W9387: =IFERROR(INDEX(Returns!A:A,MATCH(B9387,Returns!B:B,0)),"No") -> No
A9388: 9387 | B9388: US-2019-127292 | C9388: 43484 | D9388: 43488 | E9388: Standard Class | F9388: RM-19375 | G9388: Raymond Messe | H9388: Consumer | I9388: United States | J9388: Burlington | K9388: Vermont | M9388: East | N9388: OFF-PA-10000157 | O9388: Office Supplies | P9388: Paper | Q9388: Xerox 191 | R9388: 79.92 | S9388: 4 | T9388: 0 | U9388: 37.5624 | V9388: =IF(M9388=People!$B$5,People!$A$5,IF(M9388=People!$B$4,People!$A$4,IF(M9388=People!$B$3,People!$A$3,IF(M9388=People!$B$2,People!$A$2,0)))) -> Chuck Magee | W9388: =IFERROR(INDEX(Returns!A:A,MATCH(B9388,Returns!B:B,0)),"No") -> No
A9389: 9388 | B9389: US-2019-127292 | C9389: 43484 | D9389: 43488 | E9389: Standard Class | F9389: RM-19375 | G9389: Raymond Messe | H9389: Consumer | I9389: United States | J9389: Burlington | K9389: Vermont | M9389: East | N9389: OFF-PA-10001970 | O9389: Office Supplies | P9389: Paper | Q9389: Xerox 1881 | R9389: 12.28 | S9389: 1 | T9389: 0 | U9389: 5.7716 | V9389: =IF(M9389=People!$B$5,People!$A$5,IF(M9389=People!$B$4,People!$A$4,IF(M9389=People!$B$3,People!$A$3,IF(M9389=People!$B$2,People!$A$2,0)))) -> Chuck Magee | W9389: =IFERROR(INDEX(Returns!A:A,MATCH(B9389,Returns!B:B,0)),"No") -> No
A9390: 9389 | B9390: US-2019-127292 | C9390: 43484 | D9390: 43488 | E9390: Standard Class | F9390: RM-19375 | G9390: Raymond Messe | H9390: Consumer | I9390: United States | J9390: Burlington | K9390: Vermont | M9390: East | N9390: OFF-AP-10000828 | O9390: Office Supplies | P9390: Appliances | Q9390: Avanti 4.4 Cu. Ft. Refrigerator | R9390: 542.94 | S9390: 3 | T9390: 0 | U9390: 152.0232 | V9390: =IF(M9390=People!$B$5,People!$A$5,IF(M9390=People!$B$4,People!$A$4,IF(M9390=People!$B$3,People!$A$3,IF(M9390=People!$B$2,People!$A$2,0)))) -> Chuck Magee | W9390: =IFERROR(INDEX(Returns!A:A,MATCH(B9390,Returns!B:B,0)),"No") -> No
A9391: 9390 | B9391: US-2019-127292 | C9391: 43484 | D9391: 43488 | E9391: Standard Class | F9391: RM-19375 | G9391: Raymond Messe | H9391: Consumer | I9391: United States | J9391: Burlington | K9391: Vermont | M9391: East | N9391: OFF-EN-10001509 | O9391: Office Supplies | P9391: Envelopes | Q9391: Poly String Tie Envelopes | R9391: 2.04 | S9391: 1 | T9391: 0 | U9391: 0.9588 | V9391: =IF(M9391=People!$B$5,People!$A$5,IF(M9391=People!$B$4,People!$A$4,IF(M9391=People!$B$3,People!$A$3,IF(M9391=People!$B$2,People!$A$2,0)))) -> Chuck Magee | W9391: =IFERROR(INDEX(Returns!A:A,MATCH(B9391,Returns!B:B,0)),"No") -> No
A9392: 9391 | B9392: CA-2017-163734 | C9392: 42905 | D9392: 42910 | E9392: Standard Class | F9392: KM-16375 | G9392: Katherine Murray | H9392: Home Office | I9392: United States | J9392: Houston | K9392: Texas | L9392: 77070 | M9392: Central | N9392: OFF-ST-10003692 | O9392: Office Supplies | P9392: Storage | Q9392: Recycled Steel Personal File for Hanging File Folders | R9392: 228.92 | S9392: 5 | T9392: 0.2 | U9392: 14.3075 | V9392: =IF(M9392=People!$B$5,People!$A$5,IF(M9392=People!$B$4,People!$A$4,IF(M9392=People!$B$3,People!$A$3,IF(M9392=People!$B$2,People!$A$2,0)))) -> Kelly Williams | W9392: =IFERROR(INDEX(Returns!A:A,MATCH(B9392,Returns!B:B,0)),"No") -> No
A9393: 9392 | B9393: CA-2019-162474 | C9393: 43537 | D9393: 43540 | E9393: First Class | F9393: FH-14275 | G9393: Frank Hawley | H9393: Corporate | I9393: United States | J9393: Aurora | K9393: Illinois | L9393: 60505 | M9393: Central | N9393: TEC-PH-10004700 | O9393: Technology | P9393: Phones | Q9393: PowerGen Dual USB Car Charger | R9393: 7.992 | S9393: 1 | T9393: 0.2 | U9393: 2.5974 | V9393: =IF(M9393=People!$B$5,People!$A$5,IF(M9393=People!$B$4,People!$A$4,IF(M9393=People!$B$3,People!$A$3,IF(M9393=People!$B$2,People!$A$2,0)))) -> Kelly Williams | W9393: =IFERROR(INDEX(Returns!A:A,MATCH(B9393,Returns!B:B,0)),"No") -> No
A9394: 9393 | B9394: CA-2017-130848 | C9394: 43033 | D9394: 43033 | E9394: Same Day | F9394: DG-13300 | G9394: Deirdre Greer | H9394: Corporate | I9394: United States | J9394: Denver | K9394: Colorado | L9394: 80219 | M9394: West | N9394: FUR-CH-10000422 | O9394: Furniture | P9394: Chairs | Q9394: Global Highback Leather Tilter in Burgundy | R9394: 582.336 | S9394: 8 | T9394: 0.2 | U9394: -29.1168 | V9394: =IF(M9394=People!$B$5,People!$A$5,IF(M9394=People!$B$4,People!$A$4,IF(M9394=People!$B$3,People!$A$3,IF(M9394=People!$B$2,People!$A$2,0)))) -> Anna Andreadi | W9394: =IFERROR(INDEX(Returns!A:A,MATCH(B9394,Returns!B:B,0)),"No") -> No
A9395: 9394 | B9395: CA-2016-125997 | C9395: 42633 | D9395: 42636 | E9395: First Class | F9395: MW-18220 | G9395: Mitch Webber | H9395: Consumer | I9395: United States | J9395: New York City | K9395: New York | L9395: 10011 | M9395: East | N9395: TEC-PH-10003484 | O9395: Technology | P9395: Phones | Q9395: Ooma Telo VoIP Home Phone System | R9395: 629.95 | S9395: 5 | T9395: 0 | U9395: 157.4875 | V9395: =IF(M9395=People!$B$5,People!$A$5,IF(M9395=People!$B$4,People!$A$4,IF(M9395=People!$B$3,People!$A$3,IF(M9395=People!$B$2,People!$A$2,0)))) -> Chuck Magee | W9395: =IFERROR(INDEX(Returns!A:A,MATCH(B9395,Returns!B:B,0)),"No") -> No
A9396: 9395 | B9396: CA-2016-125997 | C9396: 42633 | D9396: 42636 | E9396: First Class | F9396: MW-18220 | G9396: Mitch Webber | H9396: Consumer | I9396: United States | J9396: New York City | K9396: New York | L9396: 10011 | M9396: East | N9396: FUR-CH-10001394 | O9396: Furniture | P9396: Chairs | Q9396: Global Leather Executive Chair | R9396: 631.782 | S9396: 2 | T9396: 0.1 | U9396: 140.396 | V9396: =IF(M9396=People!$B$5,People!$A$5,IF(M9396=People!$B$4,People!$A$4,IF(M9396=People!$B$3,People!$A$3,IF(M9396=People!$B$2,People!$A$2,0)))) -> Chuck Magee | W9396: =IFERROR(INDEX(Returns!A:A,MATCH(B9396,Returns!B:B,0)),"No") -> No
A9397: 9396 | B9397: CA-2016-125997 | C9397: 42633 | D9397: 42636 | E9397: First Class | F9397: MW-18220 | G9397: Mitch Webber | H9397: Consumer | I9397: United States | J9397: New York City | K9397: New York | L9397: 10011 | M9397: East | N9397: FUR-BO-10002213 | O9397: Furniture | P9397: Bookcases | Q9397: DMI Eclipse Executive Suite Bookcases | R9397: 801.568 | S9397: 2 | T9397: 0.2 | U9397: -10.0196 | V9397: =IF(M9397=People!$B$5,People!$A$5,IF(M9397=People!$B$4,People!$A$4,IF(M9397=People!$B$3,People!$A$3,IF(M9397=People!$B$2,People!$A$2,0)))) -> Chuck Magee | W9397: =IFERROR(INDEX(Returns!A:A,MATCH(B9397,Returns!B:B,0)),"No") -> No
A9398: 9397 | B9398: CA-2016-125997 | C9398: 42633 | D9398: 42636 | E9398: First Class | F9398: MW-18220 | G9398: Mitch Webber | H9398: Consumer | I9398: United States | J9398: New York City | K9398: New York | L9398: 10011 | M9398: East | N9398: OFF-LA-10002762 | O9398: Office Supplies | P9398: Labels | Q9398: Avery 485 | R9398: 75.18 | S9398: 6 | T9398: 0 | U9398: 35.3346 | V9398: =IF(M9398=People!$B$5,People!$A$5,IF(M9398=People!$B$4,People!$A$4,IF(M9398=People!$B$3,People!$A$3,IF(M9398=People!$B$2,People!$A$2,0)))) -> Chuck Magee | W9398: =IFERROR(INDEX(Returns!A:A,MATCH(B9398,Returns!B:B,0)),"No") -> No
A9399: 9398 | B9399: CA-2016-125997 | C9399: 42633 | D9399: 42636 | E9399: First Class | F9399: MW-18220 | G9399: Mitch Webber | H9399: Consumer | I9399: United States | J9399: New York City | K9399: New York | L9399: 10011 | M9399: East | N9399: OFF-AP-10003842 | O9399: Office Supplies | P9399: Appliances | Q9399: Euro-Pro Shark Turbo Vacuum | R9399: 30.98 | S9399: 1 | T9399: 0 | U9399: 8.0548 | V9399: =IF(M9399=People!$B$5,People!$A$5,IF(M9399=People!$B$4,People!$A$4,IF(M9399=People!$B$3,People!$A$3,IF(M9399=People!$B$2,People!$A$2,0)))) -> Chuck Magee | W9399: =IFERROR(INDEX(Returns!A:A,MATCH(B9399,Returns!B:B,0)),"No") -> No
A9400: 9399 | B9400: CA-2016-125997 | C9400: 42633 | D9400: 42636 | E9400: First Class | F9400: MW-18220 | G9400: Mitch Webber | H9400: Consumer | I9400: United States | J9400: New York City | K9400: New York | L9400: 10011 | M9400: East | N9400: TEC-PH-10003072 | O9400: Technology | P9400: Phones | Q9400: Panasonic KX-TG9541B DECT 6.0 Digital 2-Line Expandable Cordless Phone With Digital Answering System | R9400: 1349.91 | S9400: 9 | T9400: 0 | U9400: 661.4559 | V9400: =IF(M9400=People!$B$5,People!$A$5,IF(M9400=People!$B$4,People!$A$4,IF(M9400=People!$B$3,People!$A$3,IF(M9400=People!$B$2,People!$A$2,0)))) -> Chuck Magee | W9400: =IFERROR(INDEX(Returns!A:A,MATCH(B9400,Returns!B:B,0)),"No") -> No
A9401: 9400 | B9401: CA-2018-103128 | C9401: 43415 | D9401: 43419 | E9401: Standard Class | F9401: SC-20845 | G9401: Sung Chung | H9401: Consumer | I9401: United States | J9401: Arlington Heights | K9401: Illinois | L9401: 60004 | M9401: Central | N9401: OFF-AR-10003394 | O9401: Office Supplies | P9401: Art | Q9401: Newell 332 | R9401: 14.112 | S9401: 6 | T9401: 0.2 | U9401: 1.2348 | V9401: =IF(M9401=People!$B$5,People!$A$5,IF(M9401=People!$B$4,People!$A$4,IF(M9401=People!$B$3,People!$A$3,IF(M9401=People!$B$2,People!$A$2,0)))) -> Kelly Williams | W9401: =IFERROR(INDEX(Returns!A:A,MATCH(B9401,Returns!B:B,0)),"No") -> No
A9402: 9401 | B9402: CA-2017-167696 | C9402: 42994 | D9402: 42999 | E9402: Standard Class | F9402: BD-11500 | G9402: Bradley Drucker | H9402: Consumer | I9402: United States | J9402: Newport News | K9402: Virginia | L9402: 23602 | M9402: South | N9402: OFF-EN-10001539 | O9402: Office Supplies | P9402: Envelopes | Q9402: Staple envelope | R9402: 31.12 | S9402: 4 | T9402: 0 | U9402: 14.6264 | V9402: =IF(M9402=People!$B$5,People!$A$5,IF(M9402=People!$B$4,People!$A$4,IF(M9402=People!$B$3,People!$A$3,IF(M9402=People!$B$2,People!$A$2,0)))) -> Cassandra Brandow | W9402: =IFERROR(INDEX(Returns!A:A,MATCH(B9402,Returns!B:B,0)),"No") -> No
A9403: 9402 | B9403: CA-2016-159814 | C9403: 42545 | D9403: 42549 | E9403: Standard Class | F9403: LP-17080 | G9403: Liz Pelletier | H9403: Consumer | I9403: United States | J9403: Tucson | K9403: Arizona | L9403: 85705 | M9403: West | N9403: FUR-FU-10001731 | O9403: Furniture | P9403: Furnishings | Q9403: Acrylic Self-Standing Desk Frames | R9403: 4.272 | S9403: 2 | T9403: 0.2 | U9403: 0.9612 | V9403: =IF(M9403=People!$B$5,People!$A$5,IF(M9403=People!$B$4,People!$A$4,IF(M9403=People!$B$3,People!$A$3,IF(M9403=People!$B$2,People!$A$2,0)))) -> Anna Andreadi | W9403: =IFERROR(INDEX(Returns!A:A,MATCH(B9403,Returns!B:B,0)),"No") -> No
... A9742: 9741 | B9742: CA-2019-129294 | C9742: 43540 | D9742: 43545 | E9742: Standard Class | F9742: KD-16615 | G9742: Ken Dana | H9742: Corporate | I9742: United States | J9742: Los Angeles | K9742: California | L9742: 90032 | M9742: West | N9742: OFF-AP-10001154 | O9742: Office Supplies | P9742: Appliances | Q9742: Bionaire Personal Warm Mist Humidifier/Vaporizer | R9742: 140.67 | S9742: 3 | T9742: 0 | U9742: 54.8613 | V9742: =IF(M9742=People!$B$5,People!$A$5,IF(M9742=People!$B$4,People!$A$4,IF(M9742=People!$B$3,People!$A$3,IF(M9742=People!$B$2,People!$A$2,0)))) -> Anna Andreadi | W9742: =IFERROR(INDEX(Returns!A:A,MATCH(B9742,Returns!B:B,0)),"No") -> No
A9743: 9742 | B9743: CA-2017-117086 | C9743: 43047 | D9743: 43051 | E9743: Standard Class | F9743: QJ-19255 | G9743: Quincy Jones | H9743: Corporate | I9743: United States | J9743: Burlington | K9743: Vermont | M9743: East | N9743: FUR-BO-10004834 | O9743: Furniture | P9743: Bookcases | Q9743: Riverside Palais Royal Lawyers Bookcase, Royale Cherry Finish | R9743: 4404.9 | S9743: 5 | T9743: 0 | U9743: 1013.127 | V9743: =IF(M9743=People!$B$5,People!$A$5,IF(M9743=People!$B$4,People!$A$4,IF(M9743=People!$B$3,People!$A$3,IF(M9743=People!$B$2,People!$A$2,0)))) -> Chuck Magee | W9743: =IFERROR(INDEX(Returns!A:A,MATCH(B9743,Returns!B:B,0)),"No") -> No
A9744: 9743 | B9744: CA-2019-131303 | C9744: 43797 | D9744: 43801 | E9744: Standard Class | F9744: EP-13915 | G9744: Emily Phan | H9744: Consumer | I9744: United States | J9744: San Diego | K9744: California | L9744: 92037 | M9744: West | N9744: OFF-LA-10001074 | O9744: Office Supplies | P9744: Labels | Q9744: Round Specialty Laser Printer Labels | R9744: 62.65 | S9744: 5 | T9744: 0 | U9744: 29.4455 | V9744: =IF(M9744=People!$B$5,People!$A$5,IF(M9744=People!$B$4,People!$A$4,IF(M9744=People!$B$3,People!$A$3,IF(M9744=People!$B$2,People!$A$2,0)))) -> Anna Andreadi | W9744: =IFERROR(INDEX(Returns!A:A,MATCH(B9744,Returns!B:B,0)),"No") -> No
A9745: 9744 | B9745: CA-2018-137127 | C9745: 43267 | D9745: 43273 | E9745: Standard Class | F9745: JJ-15445 | G9745: Jennifer Jackson | H9745: Consumer | I9745: United States | J9745: Newark | K9745: Delaware | L9745: 19711 | M9745: East | N9745: OFF-LA-10001641 | O9745: Office Supplies | P9745: Labels | Q9745: Avery 518 | R9745: 9.45 | S9745: 3 | T9745: 0 | U9745: 4.536 | V9745: =IF(M9745=People!$B$5,People!$A$5,IF(M9745=People!$B$4,People!$A$4,IF(M9745=People!$B$3,People!$A$3,IF(M9745=People!$B$2,People!$A$2,0)))) -> Chuck Magee | W9745: =IFERROR(INDEX(Returns!A:A,MATCH(B9745,Returns!B:B,0)),"No") -> No
A9746: 9745 | B9746: CA-2019-141782 | C9746: 43486 | D9746: 43490 | E9746: Standard Class | F9746: BE-11410 | G9746: Bobby Elias | H9746: Consumer | I9746: United States | J9746: Aurora | K9746: Illinois | L9746: 60505 | M9746: Central | N9746: OFF-EN-10002230 | O9746: Office Supplies | P9746: Envelopes | Q9746: Airmail Envelopes | R9746: 268.576 | S9746: 4 | T9746: 0.2 | U9746: 90.6444 | V9746: =IF(M9746=People!$B$5,People!$A$5,IF(M9746=People!$B$4,People!$A$4,IF(M9746=People!$B$3,People!$A$3,IF(M9746=People!$B$2,People!$A$2,0)))) -> Kelly Williams | W9746: =IFERROR(INDEX(Returns!A:A,MATCH(B9746,Returns!B:B,0)),"No") -> No
A9747: 9746 | B9747: CA-2019-137505 | C9747: 43793 | D9747: 43793 | E9747: Same Day | F9747: BP-11290 | G9747: Beth Paige | H9747: Consumer | I9747: United States | J9747: Los Angeles | K9747: California | L9747: 90008 | M9747: West | N9747: FUR-TA-10000617 | O9747: Furniture | P9747: Tables | Q9747: Hon Practical Foundations 30 x 60 Training Table, Light Gray/Charcoal | R9747: 364.08 | S9747: 2 | T9747: 0.2 | U9747: 9.102 | V9747: =IF(M9747=People!$B$5,People!$A$5,IF(M9747=People!$B$4,People!$A$4,IF(M9747=People!$B$3,People!$A$3,IF(M9747=People!$B$2,People!$A$2,0)))) -> Anna Andreadi | W9747: =IFERROR(INDEX(Returns!A:A,MATCH(B9747,Returns!B:B,0)),"No") -> No
A9748: 9747 | B9748: CA-2019-137505 | C9748: 43793 | D9748: 43793 | E9748: Same Day | F9748: BP-11290 | G9748: Beth Paige | H9748: Consumer | I9748: United States | J9748: Los Angeles | K9748: California | L9748: 90008 | M9748: West | N9748: FUR-TA-10001676 | O9748: Furniture | P9748: Tables | Q9748: Hon 61000 Series Interactive Training Tables | R9748: 71.088 | S9748: 2 | T9748: 0.2 | U9748: -1.7772 | V9748: =IF(M9748=People!$B$5,People!$A$5,IF(M9748=People!$B$4,People!$A$4,IF(M9748=People!$B$3,People!$A$3,IF(M9748=People!$B$2,People!$A$2,0)))) -> Anna Andreadi | W9748: =IFERROR(INDEX(Returns!A:A,MATCH(B9748,Returns!B:B,0)),"No") -> No
A9749: 9748 | B9749: US-2016-140914 | C9749: 42685 | D9749: 42689 | E9749: Standard Class | F9749: BH-11710 | G9749: Brosina Hoffman | H9749: Consumer | I9749: United States | J9749: Chicago | K9749: Illinois | L9749: 60653 | M9749: Central | N9749: FUR-FU-10000175 | O9749: Furniture | P9749: Furnishings | Q9749: DAX Wood Document Frame. | R9749: 10.984 | S9749: 2 | T9749: 0.6 | U9749: -7.9634 | V9749: =IF(M9749=People!$B$5,People!$A$5,IF(M9749=People!$B$4,People!$A$4,IF(M9749=People!$B$3,People!$A$3,IF(M9749=People!$B$2,People!$A$2,0)))) -> Kelly Williams | W9749: =IFERROR(INDEX(Returns!A:A,MATCH(B9749,Returns!B:B,0)),"No") -> No
A9750: 9749 | B9750: US-2016-140914 | C9750: 42685 | D9750: 42689 | E9750: Standard Class | F9750: BH-11710 | G9750: Brosina Hoffman | H9750: Consumer | I9750: United States | J9750: Chicago | K9750: Illinois | L9750: 60653 | M9750: Central | N9750: FUR-CH-10003379 | O9750: Furniture | P9750: Chairs | Q9750: Global Commerce Series High-Back Swivel/Tilt Chairs | R9750: 797.944 | S9750: 4 | T9750: 0.3 | U9750: -56.996 | V9750: =IF(M9750=People!$B$5,People!$A$5,IF(M9750=People!$B$4,People!$A$4,IF(M9750=People!$B$3,People!$A$3,IF(M9750=People!$B$2,People!$A$2,0)))) -> Kelly Williams | W9750: =IFERROR(INDEX(Returns!A:A,MATCH(B9750,Returns!B:B,0)),"No") -> No
A9751: 9750 | B9751: CA-2018-158358 | C9751: 43163 | D9751: 43167 | E9751: Standard Class | F9751: EM-13810 | G9751: Eleni McCrary | H9751: Corporate | I9751: United States | J9751: Dover | K9751: New Hampshire | L9751: 3820 | M9751: East | N9751: TEC-AC-10002567 | O9751: Technology | P9751: Accessories | Q9751: Logitech G602 Wireless Gaming Mouse | R9751: 159.98 | S9751: 2 | T9751: 0 | U9751: 57.5928 | V9751: =IF(M9751=People!$B$5,People!$A$5,IF(M9751=People!$B$4,People!$A$4,IF(M9751=People!$B$3,People!$A$3,IF(M9751=People!$B$2,People!$A$2,0)))) -> Chuck Magee | W9751: =IFERROR(INDEX(Returns!A:A,MATCH(B9751,Returns!B:B,0)),"No") -> No
A9752: 9751 | B9752: CA-2018-113390 | C9752: 43384 | D9752: 43388 | E9752: Standard Class | F9752: EP-13915 | G9752: Emily Phan | H9752: Consumer | I9752: United States | J9752: Chicago | K9752: Illinois | L9752: 60610 | M9752: Central | N9752: OFF-AR-10003183 | O9752: Office Supplies | P9752: Art | Q9752: Avery Fluorescent Highlighter Four-Color Set | R9752: 5.344 | S9752: 2 | T9752: 0.2 | U9752: 0.668 | V9752: =IF(M9752=People!$B$5,People!$A$5,IF(M9752=People!$B$4,People!$A$4,IF(M9752=People!$B$3,People!$A$3,IF(M9752=People!$B$2,People!$A$2,0)))) -> Kelly Williams | W9752: =IFERROR(INDEX(Returns!A:A,MATCH(B9752,Returns!B:B,0)),"No") -> No
A9753: 9752 | B9753: CA-2018-113390 | C9753: 43384 | D9753: 43388 | E9753: Standard Class | F9753: EP-13915 | G9753: Emily Phan | H9753: Consumer | I9753: United States | J9753: Chicago | K9753: Illinois | L9753: 60610 | M9753: Central | N9753: OFF-AR-10001446 | O9753: Office Supplies | P9753: Art | Q9753: Newell 309 | R9753: 27.72 | S9753: 3 | T9753: 0.2 | U9753: 3.465 | V9753: =IF(M9753=People!$B$5,People!$A$5,IF(M9753=People!$B$4,People!$A$4,IF(M9753=People!$B$3,People!$A$3,IF(M9753=People!$B$2,People!$A$2,0)))) -> Kelly Williams | W9753: =IFERROR(INDEX(Returns!A:A,MATCH(B9753,Returns!B:B,0)),"No") -> No
...

Sheet People
A1: Person | B1: Region
A2: Anna Andreadi | B2: West
A3: Chuck Magee | B3: East
A4: Kelly Williams | B4: Central
A5: Cassandra Brandow | B5: South

Sheet Returns
A1: Returned | B1: Order ID
A2: Yes | B2: CA-2016-100762
A3: Yes | B3: CA-2016-100762
A4: Yes | B4: CA-2016-100762
A5: Yes | B5: CA-2016-100762
A6: Yes | B6: CA-2016-100867
A7: Yes | B7: CA-2016-102652
A8: Yes | B8: CA-2016-102652
A9: Yes | B9: CA-2016-102652
A10: Yes | B10: CA-2016-102652
A11: Yes | B11: CA-2016-103373
A12: Yes | B12: CA-2016-103744
... A801: Yes | B801: US-2019-155999

Sheet Postal Code Unique Customers
A3: Названия строк | B3: Число разных элементов в столбце Customer ID
A4: 10035 | B4: 118
A5: 10024 | B5: 115
A6: 10009 | B6: 105
A7: 94122 | B7: 95
A8: 10011 | B8: 92
A9: 94110 | B9: 82
A10: 94109 | B10: 78
A11: 98105 | B11: 74
A12: 98103 | B12: 72
A13: 19140 | B13: 69
A14: Общий итог | B14: 568

Sheet Profit by Postal code
A3: Названия строк | B3: Сумма по столбцу Profit
A4: 10024 | B4: 21653.725
A5: 10035 | B5: 16533.867 | D5: 1040 | E5: =D5 &"-0000" -> 1040-0000 | F5: 60.392
A6: 10009 | B6: 13697.002 | D6: 1453 | E6: =D6 &"-0000" -> 1453-0000 | F6: 79.5016
A7: 98115 | B7: 13303.875 | D7: 1752 | E7: =D7 &"-0000" -> 1752-0000 | F7: 67.6068
A8: 10011 | B8: 10152.39 | D8: 1810 | E8: =D8 &"-0000" -> 1810-0000 | F8: 124.1886
A9: 47905 | B9: 8976.0973 | D9: 1841 | E9: =D9 &"-0000" -> 1841-0000 | F9: 1849.4035
A10: 98105 | B10: 8734.6042 | D10: 1852 | E10: =D10 &"-0000" -> 1852-0000 | F10: 1312.5717
A11: 19711 | B11: 8086.1715 | D11: 1915 | E11: =D11 &"-0000" -> 1915-0000 | F11: 654.9194
A12: 48205 | B12: 7994.5263 | D12: 2038 | E12: =D12 &"-0000" -> 2038-0000 | F12: 464.6287
A13: 90049 | B13: 7793.1145 | D13: 2138 | E13: =D13 &"-0000" -> 2138-0000 | F13: 173.7276
A14: 94122 | B14: 7712.5958 | D14: 2148 | E14: =D14 &"-0000" -> 2148-0000 | F14: 31.1692
A15: 98103 | B15: 7117.617 | D15: 2149 | E15: =D15 &"-0000" -> 2149-0000 | F15: 1360.0809
A16: 30318 | B16: 6993.6629 | D16: 2151 | E16: =D16 &"-0000" -> 2151-0000 | F16: 258.8366
... A44: 89031 | B44: 2247.6899 | D44: 7060 | E44: =D44 &"-0000" -> 7060-0000 | F44: 1235.6657
A45: (пусто) | B45: 2244.9783 | D45: 7090 | E45: =D45 &"-0000" -> 7090-0000 | F45: 153.1758
A46: 36608 | B46: 2175.8292 | D46: 7109 | E46: =D46 &"-0000" -> 7109-0000 | F46: 283.6492
A47: 39212 | B47: 2100.4405 | D47: 7501 | E47: =D47 &"-0000" -> 7501-0000 | F47: 740.49
A48: 95823 | B48: 2069.6859 | D48: 7601 | E48: =D48 &"-0000" -> 7601-0000 | F48: 451.2547
A49: 23464 | B49: 2024.8837 | D49: 7960 | E49: =D49 &"-0000" -> 7960-0000 | F49: 1838.2271
A50: 40214 | B50: 1975.8966 | D50: 8302 | E50: =D50 &"-0000" -> 8302-0000 | F50: 3.4416
A51: 47374 | B51: 1881.862 | D51: 8360 | E51: =D51 &"-0000" -> 8360-0000 | F51: 62.2518
A52: 1841 | B52: 1849.4035 | D52: 8401 | E52: =D52 &"-0000" -> 8401-0000 | F52: 11.68
A53: 68104 | B53: 1841.6268 | D53: 8701 | E53: =D53 &"-0000" -> 8701-0000 | F53: 3526.6735
A54: 7960 | B54: 1838.2271 | D54: 8861 | E54: =D54 &"-0000" -> 8861-0000 | F54: 633.644
A55: 41042 | B55: 1837.3541 | D55: 8901 | E55: =D55 &"-0000" -> 8901-0000 | F55: 7.1567
A56: 92105 | B56: 1789.4906 | D56: 10009 | E56: =D56 &"-0000" -> 10009-0000 | F56: 13697.002
A57: 19805 | B57: 1775.0723 | D57: 10011 | E57: =D57 &"-0000" -> 10011-0000 | F57: 10152.39
... A634: 78207 | B634: -7299.0502 | D634: 99301 | E634: =D634 &"-0000" -> 99301-0000 | F634: 357.5244
A635: Общий итог | B635: 286397.02

Sheet Динамика дохода и прибыли
B3: Данные
A4: Названия строк | B4: Сумма по полю Sales | C4: Сумма по полю Profit
A5: 2016
A6: янв | B6: 14236.895 | C6: 2450.1907
A7: фев | B7: 4519.892 | C7: 862.3084
A8: мар | B8: 55691.009 | C8: 498.7299
A9: апр | B9: 28295.345 | C9: 3488.8352
A10: май | B10: 23648.287 | C10: 2738.7096
A11: июн | B11: 34595.128 | C11: 4976.5244
A12: июл | B12: 33946.393 | C12: -841.4826
A13: авг | B13: 27909.468 | C13: 5318.105
A14: сен | B14: 81777.351 | C14: 8328.0994
A15: окт | B15: 31453.393 | C15: 3448.2573
A16: ноя | B16: 78628.717 | C16: 9292.1269
A17: дек | B17: 69545.62 | C17: 8983.5699
A18: 2017
A19: янв | B19: 18174.076 | C19: -3281.007
A20: фев | B20: 11951.411 | C20: 2813.8508
A21: мар | B21: 38726.252 | C21: 9732.0978
A22: апр | B22: 34195.208 | C22: 4187.4962
A23: май | B23: 30131.686 | C23: 4667.869
A24: июн | B24: 24797.292 | C24: 3335.5572
A25: июл | B25: 28765.325 | C25: 3288.6483
A26: авг | B26: 36898.332 | C26: 5355.8084
A27: сен | B27: 64595.918 | C27: 8209.1627
A28: окт | B28: 31404.924 | C28: 2817.366
A29: ноя | B29: 75972.564 | C29: 12474.788
A30: дек | B30: 74919.521 | C30: 8016.9659
A31: 2018
A32: янв | B32: 18542.491 | C32: 2824.8233
A33: фев | B33: 22978.815 | C33: 5004.5795
A34: мар | B34: 51715.875 | C34: 3611.968
A35: апр | B35: 38750.039 | C35: 2977.8149
A36: май | B36: 56987.728 | C36: 8662.1464
A37: июн | B37: 40344.534 | C37: 4750.3781
A38: июл | B38: 39261.963 | C38: 4432.8779
A39: авг | B39: 31115.374 | C39: 2062.0693
A40: сен | B40: 73410.025 | C40: 9328.6576
A41: окт | B41: 59687.745 | C41: 16243.143
A42: ноя | B42: 79411.966 | C42: 4011.4075
A43: дек | B43: 96999.043 | C43: 17885.309
A44: 2019
A45: янв | B45: 43971.374 | C45: 7140.4391
A46: фев | B46: 20301.133 | C46: 1613.872
A47: мар | B47: 58872.353 | C47: 14751.891
A48: апр | B48: 36521.536 | C48: 933.29
A49: май | B49: 44261.11 | C49: 6342.5828
A50: июн | B50: 52981.726 | C50: 8223.3357
A51: июл | B51: 45264.416 | C51: 6952.6212
A52: авг | B52: 63120.888 | C52: 9040.9557
A53: сен | B53: 87866.652 | C53: 10991.556
A54: окт | B54: 77776.923 | C54: 9275.2755
A55: ноя | B55: 118447.83 | C55: 9690.1037
A56: дек | B56: 83829.319 | C56: 8483.3468
A57: Общий итог | B57: 2297200.9 | C57: 286397.02

Sheet Sales by Category
A3: Названия строк | B3: Сумма по столбцу Sales
A4: Furniture | B4: 741999.8
A5: Office Supplies | B5: 719047.03
A6: Technology | B6: 836154.03
A7: Общий итог | B7: 2297200.9

Sheet Sales by Segment
A3: Названия строк | B3: Сумма по столбцу Sales
A4: Consumer | B4: 1161401.3
A5: Corporate | B5: 706146.37
A6: Home Office | B6: 429653.15
A7: Общий итог | B7: 2297200.9

Sheet Monthly Sales Segment
A2: Region | B2: (Все)
A4: Сумма по полю Sales | C4: Segment
A5: Годы | B5: Order Date | C5: Consumer | D5: Corporate | E5: Home Office | F5: Общий итог
A6: 2016 | B6: янв | C6: 6927.817 | D6: 1701.528 | E6: 5607.55 | F6: 14236.895
B7: фев | C7: 3167.854 | D7: 1183.668 | E7: 168.37 | F7: 4519.892
B8: мар | C8: 11869.304 | D8: 11106.799 | E8: 32714.906 | F8: 55691.009
B9: апр | C9: 9108.612 | D9: 14131.729 | E9: 5055.004 | F9: 28295.345
B10: май | C10: 12819.163 | D10: 9142 | E10: 1687.124 | F10: 23648.287
B11: июн | C11: 25923.748 | D11: 3970.914 | E11: 4700.466 | F11: 34595.128
B12: июл | C12: 20197.74 | D12: 10032.988 | E12: 3715.665 | F12: 33946.393
B13: авг | C13: 16215.263 | D13: 7451.774 | E13: 4242.431 | F13: 27909.468
B14: сен | C14: 59690.65 | D14: 15507.745 | E14: 6578.9558 | F14: 81777.351
B15: окт | C15: 16246.697 | D15: 12637.678 | E15: 2569.018 | F15: 31453.393
B16: ноя | C16: 46571.978 | D16: 20994.495 | E16: 11062.244 | F16: 78628.717
B17: дек | C17: 37357.986 | D17: 20573.556 | E17: 11614.078 | F17: 69545.62
A18: 2017 | B18: янв | C18: 14274.984 | D18: 3382.464 | E18: 516.628 | F18: 18174.076
B19: фев | C19: 9269.018 | D19: 2565.257 | E19: 117.136 | F19: 11951.411
B20: мар | C20: 17418.89 | D20: 16332.018 | E20: 4975.3436 | F20: 38726.252
B21: апр | C21: 22626.405 | D21: 4121.044 | E21: 7447.759 | F21: 34195.208
B22: май | C22: 20879.179 | D22: 5454.9395 | E22: 3797.568 | F22: 30131.686
B23: июн | C23: 12824.504 | D23: 9404.089 | E23: 2568.699 | F23: 24797.292
B24: июл | C24: 19948.813 | D24: 7191.7 | E24: 1624.812 | F24: 28765.325
B25: авг | C25: 20589.835 | D25: 11455.759 | E25: 4852.738 | F25: 36898.332
B26: сен | C26: 38860.273 | D26: 16604.561 | E26: 9131.084 | F26: 64595.918
B27: окт | C27: 17128.868 | D27: 8646.369 | E27: 5629.686 | F27: 31404.923
B28: ноя | C28: 33146.833 | D28: 27299.645 | E28: 15526.086 | F28: 75972.563
B29: дек | C29: 39568.331 | D29: 16299.461 | E29: 19051.729 | F29: 74919.521
A30: 2018 | B30: янв | C30: 6026.649 | D30: 9485.124 | E30: 3030.718 | F30: 18542.491
B31: фев | C31: 15800.227 | D31: 2866.884 | E31: 4311.704 | F31: 22978.815
B32: мар | C32: 24844.991 | D32: 14226.473 | E32: 12644.411 | F32: 51715.875
B33: апр | C33: 14075.248 | D33: 16177.376 | E33: 8497.415 | F33: 38750.039
B34: май | C34: 32174.635 | D34: 18452.258 | E34: 6360.835 | F34: 56987.728
B35: июн | C35: 23888.811 | D35: 7788.494 | E35: 8667.229 | F35: 40344.534
B36: июл | C36: 22631.847 | D36: 13168.919 | E36: 3461.197 | F36: 39261.963
B37: авг | C37: 13885.564 | D37: 12943.471 | E37: 4286.34 | F37: 31115.374
B38: сен | C38: 42647.794 | D38: 17802.812 | E38: 12959.419 | F38: 73410.025
B39: окт | C39: 10143.282 | D39: 32130.545 | E39: 17413.918 | F39: 59687.745
B40: ноя | C40: 41449.863 | D40: 26493.18 | E40: 11468.923 | F40: 79411.966
B41: дек | C41: 49294.989 | D41: 35570.826 | E41: 12133.228 | F41: 96999.043
A42: 2019 | B42: янв | C42: 23211.841 | D42: 12221.232 | E42: 8538.301 | F42: 43971.374
B43: фев | C43: 5589.077 | D43: 7959.258 | E43: 6752.7984 | F43: 20301.133
B44: мар | C44: 35041.522 | D44: 16574.623 | E44: 7256.208 | F44: 58872.353
B45: апр | C45: 9034.924 | D45: 14803.015 | E45: 12683.597 | F45: 36521.536
B46: май | C46: 21059.737 | D46: 14239.835 | E46: 8961.538 | F46: 44261.11
B47: июн | C47: 20273.118 | D47: 19695.04 | E47: 13013.568 | F47: 52981.726
B48: июл | C48: 18991.373 | D48: 16525.599 | E48: 9747.444 | F48: 45264.416
B49: авг | C49: 31629.144 | D49: 25678.444 | E49: 5813.3 | F49: 63120.888
B50: сен | C50: 43857.203 | D50: 24105.103 | E50: 19904.346 | F50: 87866.652
B51: окт | C51: 23194.24 | D51: 24877.168 | E51: 29705.515 | F51: 77776.923
B52: ноя | C52: 49790.065 | D52: 44644.076 | E52: 24013.684 | F52: 118447.82
B53: дек | C53: 50232.456 | D53: 20524.432 | E53: 13072.431 | F53: 83829.319
A54: Общий итог | C54: 1161401.3 | D54: 706146.37 | E54: 429653.15 | F54: 2297200.9

Sheet Monthly Sales Product Category
A1: Region | B1: (Все)
A3: Сумма по полю Sales | C3: Category
A4: Годы | B4: Order Date | C4: Furniture | D4: Office Supplies | E4: Technology | F4: Общий итог
A5: 2016 | B5: янв | C5: 6242.525 | D5: 4851.08 | E5: 3143.29 | F5: 14236.895
B6: фев | C6: 1839.658 | D6: 1071.724 | E6: 1608.51 | F6: 4519.892
B7: мар | C7: 14573.956 | D7: 8605.879 | E7: 32511.174 | F7: 55691.009
B8: апр | C8: 7944.837 | D8: 11155.074 | E8: 9195.434 | F8: 28295.345
B9: май | C9: 6912.787 | D9: 7135.624 | E9: 9599.876 | F9: 23648.287
B10: июн | C10: 13206.126 | D10: 12953.037 | E10: 8435.965 | F10: 34595.128
B11: июл | C11: 10821.051 | D11: 15121.208 | E11: 8004.134 | F11: 33946.393
B12: авг | C12: 7320.3465 | D12: 11379.462 | E12: 9209.66 | F12: 27909.469
B13: сен | C13: 23816.481 | D13: 27423.298 | E13: 30537.572 | F13: 81777.351
B14: окт | C14: 12304.247 | D14: 7211.128 | E14: 11938.018 | F14: 31453.393
B15: ноя | C15: 21564.873 | D15: 26862.436 | E15: 30201.408 | F15: 78628.717
B16: дек | C16: 30645.967 | D16: 18006.462 | E16: 20893.192 | F16: 69545.621
A17: 2016 Итог | C17: 157192.85 | D17: 151776.41 | E17: 175278.23 | F17: 484247.5
A18: 2017 | B18: янв | C18: 11739.942 | D18: 1808.78 | E18: 4625.354 | F18: 18174.076
B19: фев | C19: 3134.374 | D19: 5368.067 | E19: 3448.97 | F19: 11951.411
B20: мар | C20: 12499.783 | D20: 15882.547 | E20: 10343.922 | F20: 38726.252
B21: апр | C21: 10475.698 | D21: 12558.558 | E21: 11160.952 | F21: 34195.209
B22: май | C22: 9374.9505 | D22: 9113.736 | E22: 11643 | F22: 30131.687
B23: июн | C23: 7714.179 | D23: 10647.747 | E23: 6435.366 | F23: 24797.292
B24: июл | C24: 13674.42 | D24: 4719.939 | E24: 10370.966 | F24: 28765.325
B25: авг | C25: 9638.5922 | D25: 11735.108 | E25: 15524.632 | F25: 36898.332
B26: сен | C26: 26273.023 | D26: 19305.767 | E26: 19017.128 | F26: 64595.918
B27: окт | C27: 12026.624 | D27: 8673.41 | E27: 10704.89 | F27: 31404.923
B28: ноя | C28: 30880.832 | D28: 21218.13 | E28: 23873.601 | F28: 75972.563
B29: дек | C29: 23085.819 | D29: 16201.674 | E29: 35632.028 | F29: 74919.521
A30: 2017 Итог | C30: 170518.24 | D30: 137233.46 | E30: 162780.81 | F30: 470532.51
A31: 2018 | B31: янв | C31: 7622.743 | D31: 5299.682 | E31: 5620.066 | F31: 18542.491
B32: фев | C32: 3925.551 | D32: 6794.35 | E32: 12258.914 | F32: 22978.815
B33: мар | C33: 12801.092 | D33: 17346.931 | E33: 21567.852 | F33: 51715.875
B34: апр | C34: 13212.09 | D34: 10647.447 | E34: 14890.502 | F34: 38750.039
B35: май | C35: 15119.835 | D35: 13035.202 | E35: 28832.691 | F35: 56987.728
B36: июн | C36: 13070.572 | D36: 10901.81 | E36: 16372.152 | F36: 40344.534
B37: июл | C37: 13068.519 | D37: 12924.444 | E37: 13269 | F37: 39261.963
B38: авг | C38: 12483.232 | D38: 8959.74 | E38: 9672.402 | F38: 31115.374
B39: сен | C39: 27262.881 | D39: 23263.738 | E39: 22883.406 | F39: 73410.025
B40: окт | C40: 11872.577 | D40: 16281.794 | E40: 31533.374 | F40: 59687.745
B41: ноя | C41: 31783.629 | D41: 20487.278 | E41: 27141.059 | F41: 79411.966
B42: дек | C42: 36678.715 | D42: 37997.566 | E42: 22322.762 | F42: 96999.043
A43: 2018 Итог | C43: 198901.44 | D43: 183939.98 | E43: 226364.18 | F43: 609205.6
A44: 2019 | B44: янв | C44: 5964.032 | D44: 21274.289 | E44: 16733.053 | F44: 43971.374
B45: фев | C45: 6866.3374 | D45: 7407.772 | E45: 6027.024 | F45: 20301.133
B46: мар | C46: 10893.445 | D46: 14550.286 | E46: 33428.622 | F46: 58872.353
B47: апр | C47: 9065.9581 | D47: 15072.191 | E47: 12383.387 | F47: 36521.536
B48: май | C48: 16957.558 | D48: 13736.964 | E48: 13566.588 | F48: 44261.11
B49: июн | C49: 19008.587 | D49: 16912.039 | E49: 17061.1 | F49: 52981.726
B50: июл | C50: 11813.022 | D50: 10241.468 | E50: 23209.926 | F50: 45264.416
B51: авг | C51: 15441.874 | D51: 30059.852 | E51: 17619.162 | F51: 63120.888
B52: сен | C52: 29028.206 | D52: 31895.843 | E52: 26942.603 | F52: 87866.652
B53: окт | C53: 21884.068 | D53: 23037.192 | E53: 32855.663 | F53: 77776.923
B54: ноя | C54: 37056.715 | D54: 31472.337 | E54: 49918.773 | F54: 118447.82
B55: дек | C55: 31407.467 | D55: 30436.942 | E55: 21984.91 | F55: 83829.319
A56: 2019 Итог | C56: 215387.27 | D56: 246097.17 | E56: 271730.81 | F56: 733215.26
A57: Общий итог | C57: 741999.8 | D57: 719047.03 | E57: 836154.03 | F57: 2297200.9

Sheet Customer Ranking
A1: Segment | B1: (Все)
A2: Region | B2: (Все)
A4: Сумма по полю Sales
A5: Customer Name | B5: Итог
A6: Sean Miller | B6: 25043.05
A7: Tamara Chand | B7: 19052.218
A8: Raymond Buch | B8: 15117.339
A9: Tom Ashbrook | B9: 14595.62
A10: Adrian Barton | B10: 14473.571
A11: Ken Lonsdale | B11: 14175.229
A12: Sanjit Chand | B12: 14142.334
A13: Hunter Lopez | B13: 12873.298
A14: Sanjit Engle | B14: 12209.438
A15: Christopher Conant | B15: 12129.072
A16: Общий итог | B16: 153811.17

Sheet Profit by State
A3: Названия строк | B3: Сумма по столбцу Profit
A4: Alabama | B4: 5786.8253
A5: Arizona | B5: -3427.9246
A6: Arkansas | B6: 4008.6871
A7: California | B7: 76381.387
A8: Colorado | B8: -6527.8579
A9: Connecticut | B9: 3511.4918
A10: Delaware | B10: 9977.3748
A11: District of Columbia | B11: 1059.5893
A12: Florida | B12: -3399.3017
A13: Georgia | B13: 16250.043
A14: Idaho | B14: 826.7231
A15: Illinois | B15: -12607.887
... A53: Общий итог | B53: 286397.02
C185: Alabama | D185: 5786.8253
C186: Arizona | D186: -3427.9246
C187: Arkansas | D187: 4008.6871
C188: California | D188: 76381.387
C189: Colorado | D189: -6527.8579
C190: Connecticut | D190: 3511.4918
C191: Delaware | D191: 9977.3748
C192: District of Columbia | D192: 1059.5893
C193: Florida | D193: -3399.3017
C194: Georgia | D194: 16250.043
C195: Idaho | D195: 826.7231
C196: Illinois | D196: -12607.887
... C233: Wyoming | D233: 100.196
